<XMBML version="1.0">
<View id="F_games">
<Attributes>
<Table key="psnstuff_PSN_EU_item_174">
                <Pair key="icon"><String>/dev_hdd0/game/DARKSTORE/USRDIR/games/ps3list/IMG/F1 2012.png</String></Pair>
                <Pair key="title"><String>F1 2012</String></Pair>
                <Pair key="info"><String>NPEB01107 - 7247.11 Mb</String></Pair>
                <Pair key="ingame"><String>disable</String></Pair>
            </Table>
            <Table key="psnstuff_PSN_EU_item_175">
                <Pair key="icon"><String>/dev_hdd0/game/DARKSTORE/USRDIR/games/ps3list/IMG/F1 2013.png</String></Pair>
                <Pair key="title"><String>F1 2013</String></Pair>
                <Pair key="info"><String>NPEB01791 - 8604.28 Mb</String></Pair>
                <Pair key="ingame"><String>disable</String></Pair>
            </Table>
            <Table key="psnstuff_PSN_EU_item_176">
                <Pair key="icon"><String>/dev_hdd0/game/DARKSTORE/USRDIR/icons/download.png</String></Pair>
                <Pair key="title"><String>F1 2014</String></Pair>
                <Pair key="info"><String>NPEB02094 - 4619.66 Mb</String></Pair>
                <Pair key="ingame"><String>disable</String></Pair>
            </Table>
            <Table key="psnstuff_PSN_EU_item_177">
                <Pair key="icon"><String>/dev_hdd0/game/DARKSTORE/USRDIR/games/ps3list/IMG/F1 Race Stars.png</String></Pair>
                <Pair key="title"><String>F1 Race Stars</String></Pair>
                <Pair key="info"><String>NPEB01124 - 1174.42 Mb</String></Pair>
                <Pair key="ingame"><String>disable</String></Pair>
            </Table>
            <Table key="psnstuff_PSN_EU_item_178">
                <Pair key="icon"><String>/dev_hdd0/game/DARKSTORE/USRDIR/icons/download.png</String></Pair>
                <Pair key="title"><String>Fairy Fencer F - Full Game</String></Pair>
                <Pair key="info"><String>NPEB01999 - 4528.26 Mb</String></Pair>
                <Pair key="ingame"><String>disable</String></Pair>
            </Table>
            <Table key="psnstuff_PSN_EU_item_179">
                <Pair key="icon"><String>/dev_hdd0/game/DARKSTORE/USRDIR/games/ps3list/IMG/Far Cry 2.png</String></Pair>
                <Pair key="title"><String>Far Cry 2</String></Pair>
                <Pair key="info"><String>NPEB00599 - 3938.94 Mb</String></Pair>
                <Pair key="ingame"><String>disable</String></Pair>
            </Table>
            <Table key="psnstuff_PSN_EU_item_180">
                <Pair key="icon"><String>/dev_hdd0/game/DARKSTORE/USRDIR/games/ps3list/IMG/Far Cry 3.png</String></Pair>
                <Pair key="title"><String>Far Cry 3</String></Pair>
                <Pair key="info"><String>NPEB01096 - 6403.63 Mb</String></Pair>
                <Pair key="ingame"><String>disable</String></Pair>
            </Table>
            <Table key="psnstuff_PSN_EU_item_181">
                <Pair key="icon"><String>/dev_hdd0/game/DARKSTORE/USRDIR/games/ps3list/IMG/Farming Simulator 15.png</String></Pair>
                <Pair key="title"><String>Farming Simulator 15</String></Pair>
                <Pair key="info"><String>NPEB02151 - 401.95 Mb</String></Pair>
                <Pair key="ingame"><String>disable</String></Pair>
            </Table>
            <Table key="psnstuff_PSN_EU_item_182">
                <Pair key="icon"><String>/dev_hdd0/game/DARKSTORE/USRDIR/games/ps3list/IMG/Fast Draw Shotdown.png</String></Pair>
                <Pair key="title"><String>Fast Draw Shotdown</String></Pair>
                <Pair key="info"><String>NPEB00437 - 699.20 Mb</String></Pair>
                <Pair key="ingame"><String>disable</String></Pair>
            </Table>
            <Table key="psnstuff_PSN_EU_item_183">
                <Pair key="icon"><String>/dev_hdd0/game/DARKSTORE/USRDIR/games/ps3list/IMG/Fat Princess.png</String></Pair>
                <Pair key="title"><String>Fat Princess</String></Pair>
                <Pair key="info"><String>NPEA00111 - 364.95 Mb</String></Pair>
                <Pair key="ingame"><String>disable</String></Pair>
            </Table>
            <Table key="psnstuff_PSN_EU_item_184">
                <Pair key="icon"><String>/dev_hdd0/game/DARKSTORE/USRDIR/games/ps3list/IMG/Ferrari The Race Experience.png</String></Pair>
                <Pair key="title"><String>Ferrari The Race Experience</String></Pair>
                <Pair key="info"><String>NPEB00185 - 2196.06 Mb</String></Pair>
                <Pair key="ingame"><String>disable</String></Pair>
            </Table>
            <Table key="psnstuff_PSN_EU_item_185">
                <Pair key="icon"><String>/dev_hdd0/game/DARKSTORE/USRDIR/games/ps3list/IMG/Fifa 12.png</String></Pair>
                <Pair key="title"><String>Fifa 12</String></Pair>
                <Pair key="info"><String>NPEB00688 - 9121.10 Mb</String></Pair>
                <Pair key="ingame"><String>disable</String></Pair>
            </Table>
            <Table key="psnstuff_PSN_EU_item_186">
                <Pair key="icon"><String>/dev_hdd0/game/DARKSTORE/USRDIR/games/ps3list/IMG/FIFA 14.png</String></Pair>
                <Pair key="title"><String>FIFA 14</String></Pair>
                <Pair key="info"><String>NPEB01384 - 9931.78 Mb</String></Pair>
                <Pair key="ingame"><String>disable</String></Pair>
            </Table>
            <Table key="psnstuff_PSN_EU_item_187">
                <Pair key="icon"><String>/dev_hdd0/game/DARKSTORE/USRDIR/games/ps3list/IMG/FIFA 14 - World Cup Brazil.png</String></Pair>
                <Pair key="title"><String>FIFA 14 - World Cup Brazil</String></Pair>
                <Pair key="info"><String>NPEB01947 - 6719.00 Mb</String></Pair>
                <Pair key="ingame"><String>disable</String></Pair>
            </Table>
            <Table key="psnstuff_PSN_EU_item_188">
                <Pair key="icon"><String>/dev_hdd0/game/DARKSTORE/USRDIR/games/ps3list/IMG/FIFA 15.png</String></Pair>
                <Pair key="title"><String>FIFA 15</String></Pair>
                <Pair key="info"><String>NPEB02045 - 10404.26 Mb</String></Pair>
                <Pair key="ingame"><String>disable</String></Pair>
            </Table>
            <Table key="psnstuff_PSN_EU_item_189">
                <Pair key="icon"><String>/dev_hdd0/game/DARKSTORE/USRDIR/icons/download.png</String></Pair>
                <Pair key="title"><String>FIFA 16</String></Pair>
                <Pair key="info"><String>NPEB02258 - 9538.43 Mb</String></Pair>
                <Pair key="ingame"><String>disable</String></Pair>
            </Table>
            <Table key="psnstuff_PSN_EU_item_190">
                <Pair key="icon"><String>/dev_hdd0/game/DARKSTORE/USRDIR/games/ps3list/IMG/FIFA Street.png</String></Pair>
                <Pair key="title"><String>FIFA Street</String></Pair>
                <Pair key="info"><String>NPEB00822 - 4568.69 Mb</String></Pair>
                <Pair key="ingame"><String>disable</String></Pair>
            </Table>
            <Table key="psnstuff_PSN_EU_item_191">
                <Pair key="icon"><String>/dev_hdd0/game/DARKSTORE/USRDIR/icons/download.png</String></Pair>
                <Pair key="title"><String>Fighting Vipers</String></Pair>
                <Pair key="info"><String>NPEB01164 - 67.16 Mb</String></Pair>
                <Pair key="ingame"><String>disable</String></Pair>
            </Table>
            <Table key="psnstuff_PSN_EU_item_192">
                <Pair key="icon"><String>/dev_hdd0/game/DARKSTORE/USRDIR/games/ps3list/IMG/Final Fantasy X and X-2 HD Remaster.png</String></Pair>
                <Pair key="title"><String>Final Fantasy X and X-2 HD Remaster</String></Pair>
                <Pair key="info"><String>NPEB01391 - 23441.22 Mb</String></Pair>
                <Pair key="ingame"><String>disable</String></Pair>
            </Table>
            <Table key="psnstuff_PSN_EU_item_193">
                <Pair key="icon"><String>/dev_hdd0/game/DARKSTORE/USRDIR/games/ps3list/IMG/Final Fight - Double Impact.png</String></Pair>
                <Pair key="title"><String>Final Fight: Double Impact</String></Pair>
                <Pair key="info"><String>NPEB00168 - 256.09 Mb</String></Pair>
                <Pair key="ingame"><String>disable</String></Pair>
            </Table>
            <Table key="psnstuff_PSN_EU_item_194">
                <Pair key="icon"><String>/dev_hdd0/game/DARKSTORE/USRDIR/games/ps3list/IMG/FirstPlay Episode 002.png</String></Pair>
                <Pair key="title"><String>FirstPlay Episode 002</String></Pair>
                <Pair key="info"><String>NPEB00195 - 988.41 Mb</String></Pair>
                <Pair key="ingame"><String>disable</String></Pair>
            </Table>
            <Table key="psnstuff_PSN_EU_item_195">
                <Pair key="icon"><String>/dev_hdd0/game/DARKSTORE/USRDIR/games/ps3list/IMG/flOw.png</String></Pair>
                <Pair key="title"><String>flOw</String></Pair>
                <Pair key="info"><String>NPEA00021 - 127.11 Mb</String></Pair>
                <Pair key="ingame"><String>disable</String></Pair>
            </Table>
            <Table key="psnstuff_PSN_EU_item_196">
                <Pair key="icon"><String>/dev_hdd0/game/DARKSTORE/USRDIR/games/ps3list/IMG/flOw.png</String></Pair>
                <Pair key="title"><String>flOw</String></Pair>
                <Pair key="info"><String>NPEA00021 - 130.87 Mb</String></Pair>
                <Pair key="ingame"><String>disable</String></Pair>
            </Table>
            <Table key="psnstuff_PSN_EU_item_197">
                <Pair key="icon"><String>/dev_hdd0/game/DARKSTORE/USRDIR/games/ps3list/IMG/Flower.png</String></Pair>
                <Pair key="title"><String>Flower</String></Pair>
                <Pair key="info"><String>NPEA00094 - 626.78 Mb</String></Pair>
                <Pair key="ingame"><String>disable</String></Pair>
            </Table>
            <Table key="psnstuff_PSN_EU_item_198">
                <Pair key="icon"><String>/dev_hdd0/game/DARKSTORE/USRDIR/games/ps3list/IMG/Flower.png</String></Pair>
                <Pair key="title"><String>Flower</String></Pair>
                <Pair key="info"><String>NPEA00094 - 626.78 Mb</String></Pair>
                <Pair key="ingame"><String>disable</String></Pair>
            </Table>
            <Table key="psnstuff_PSN_EU_item_199">
                <Pair key="icon"><String>/dev_hdd0/game/DARKSTORE/USRDIR/games/ps3list/IMG/Frogger Returns.png</String></Pair>
                <Pair key="title"><String>Frogger Returns</String></Pair>
                <Pair key="info"><String>NPEB00162 - 45.69 Mb</String></Pair>
                <Pair key="ingame"><String>disable</String></Pair>
            </Table>
            <Table key="psnstuff_PSN_EU_item_200">
                <Pair key="icon"><String>/dev_hdd0/game/DARKSTORE/USRDIR/games/ps3list/IMG/Frozen Synapse Prime.png</String></Pair>
                <Pair key="title"><String>Frozen Synapse Prime</String></Pair>
                <Pair key="info"><String>NPEB01361 - 294.26 Mb</String></Pair>
                <Pair key="ingame"><String>disable</String></Pair>
            </Table>
            <Table key="psnstuff_PSN_EU_item_201">
                <Pair key="icon"><String>/dev_hdd0/game/DARKSTORE/USRDIR/games/ps3list/IMG/FUEL Overdose.png</String></Pair>
                <Pair key="title"><String>FUEL Overdose</String></Pair>
                <Pair key="info"><String>NPEB00876 - 235.93 Mb</String></Pair>
                <Pair key="ingame"><String>disable</String></Pair>
            </Table>

</Attributes>

<Items>
<Query
                class="type:x-xmb/folder-pixmap"
                key="psnstuff_PSN_EU_item_174"
                attr="psnstuff_PSN_EU_item_174"
                src="#psnstuff_PSN_EU_item_174_link"
            />
            <Query
                class="type:x-xmb/folder-pixmap"
                key="psnstuff_PSN_EU_item_175"
                attr="psnstuff_PSN_EU_item_175"
                src="#psnstuff_PSN_EU_item_175_link"
            />
            <Query
                class="type:x-xmb/folder-pixmap"
                key="psnstuff_PSN_EU_item_176"
                attr="psnstuff_PSN_EU_item_176"
                src="#psnstuff_PSN_EU_item_176_link"
            />
            <Query
                class="type:x-xmb/folder-pixmap"
                key="psnstuff_PSN_EU_item_177"
                attr="psnstuff_PSN_EU_item_177"
                src="#psnstuff_PSN_EU_item_177_link"
            />
            <Query
                class="type:x-xmb/folder-pixmap"
                key="psnstuff_PSN_EU_item_178"
                attr="psnstuff_PSN_EU_item_178"
                src="#psnstuff_PSN_EU_item_178_link"
            />
            <Query
                class="type:x-xmb/folder-pixmap"
                key="psnstuff_PSN_EU_item_179"
                attr="psnstuff_PSN_EU_item_179"
                src="#psnstuff_PSN_EU_item_179_link"
            />
            <Query
                class="type:x-xmb/folder-pixmap"
                key="psnstuff_PSN_EU_item_180"
                attr="psnstuff_PSN_EU_item_180"
                src="#psnstuff_PSN_EU_item_180_link"
            />
            <Query
                class="type:x-xmb/folder-pixmap"
                key="psnstuff_PSN_EU_item_181"
                attr="psnstuff_PSN_EU_item_181"
                src="#psnstuff_PSN_EU_item_181_link"
            />
            <Query
                class="type:x-xmb/folder-pixmap"
                key="psnstuff_PSN_EU_item_182"
                attr="psnstuff_PSN_EU_item_182"
                src="#psnstuff_PSN_EU_item_182_link"
            />
            <Query
                class="type:x-xmb/folder-pixmap"
                key="psnstuff_PSN_EU_item_183"
                attr="psnstuff_PSN_EU_item_183"
                src="#psnstuff_PSN_EU_item_183_link"
            />
            <Query
                class="type:x-xmb/folder-pixmap"
                key="psnstuff_PSN_EU_item_184"
                attr="psnstuff_PSN_EU_item_184"
                src="#psnstuff_PSN_EU_item_184_link"
            />
            <Query
                class="type:x-xmb/folder-pixmap"
                key="psnstuff_PSN_EU_item_185"
                attr="psnstuff_PSN_EU_item_185"
                src="#psnstuff_PSN_EU_item_185_link"
            />
            <Query
                class="type:x-xmb/folder-pixmap"
                key="psnstuff_PSN_EU_item_186"
                attr="psnstuff_PSN_EU_item_186"
                src="#psnstuff_PSN_EU_item_186_link"
            />
            <Query
                class="type:x-xmb/folder-pixmap"
                key="psnstuff_PSN_EU_item_187"
                attr="psnstuff_PSN_EU_item_187"
                src="#psnstuff_PSN_EU_item_187_link"
            />
            <Query
                class="type:x-xmb/folder-pixmap"
                key="psnstuff_PSN_EU_item_188"
                attr="psnstuff_PSN_EU_item_188"
                src="#psnstuff_PSN_EU_item_188_link"
            />
            <Query
                class="type:x-xmb/folder-pixmap"
                key="psnstuff_PSN_EU_item_189"
                attr="psnstuff_PSN_EU_item_189"
                src="#psnstuff_PSN_EU_item_189_link"
            />
            <Query
                class="type:x-xmb/folder-pixmap"
                key="psnstuff_PSN_EU_item_190"
                attr="psnstuff_PSN_EU_item_190"
                src="#psnstuff_PSN_EU_item_190_link"
            />
            <Query
                class="type:x-xmb/folder-pixmap"
                key="psnstuff_PSN_EU_item_191"
                attr="psnstuff_PSN_EU_item_191"
                src="#psnstuff_PSN_EU_item_191_link"
            />
            <Query
                class="type:x-xmb/folder-pixmap"
                key="psnstuff_PSN_EU_item_192"
                attr="psnstuff_PSN_EU_item_192"
                src="#psnstuff_PSN_EU_item_192_link"
            />
            <Query
                class="type:x-xmb/folder-pixmap"
                key="psnstuff_PSN_EU_item_193"
                attr="psnstuff_PSN_EU_item_193"
                src="#psnstuff_PSN_EU_item_193_link"
            />
            <Query
                class="type:x-xmb/folder-pixmap"
                key="psnstuff_PSN_EU_item_194"
                attr="psnstuff_PSN_EU_item_194"
                src="#psnstuff_PSN_EU_item_194_link"
            />
            <Query
                class="type:x-xmb/folder-pixmap"
                key="psnstuff_PSN_EU_item_195"
                attr="psnstuff_PSN_EU_item_195"
                src="#psnstuff_PSN_EU_item_195_link"
            />
            <Query
                class="type:x-xmb/folder-pixmap"
                key="psnstuff_PSN_EU_item_196"
                attr="psnstuff_PSN_EU_item_196"
                src="#psnstuff_PSN_EU_item_196_link"
            />
            <Query
                class="type:x-xmb/folder-pixmap"
                key="psnstuff_PSN_EU_item_197"
                attr="psnstuff_PSN_EU_item_197"
                src="#psnstuff_PSN_EU_item_197_link"
            />
            <Query
                class="type:x-xmb/folder-pixmap"
                key="psnstuff_PSN_EU_item_198"
                attr="psnstuff_PSN_EU_item_198"
                src="#psnstuff_PSN_EU_item_198_link"
            />
            <Query
                class="type:x-xmb/folder-pixmap"
                key="psnstuff_PSN_EU_item_199"
                attr="psnstuff_PSN_EU_item_199"
                src="#psnstuff_PSN_EU_item_199_link"
            />
            <Query
                class="type:x-xmb/folder-pixmap"
                key="psnstuff_PSN_EU_item_200"
                attr="psnstuff_PSN_EU_item_200"
                src="#psnstuff_PSN_EU_item_200_link"
            />
            <Query
                class="type:x-xmb/folder-pixmap"
                key="psnstuff_PSN_EU_item_201"
                attr="psnstuff_PSN_EU_item_201"
                src="#psnstuff_PSN_EU_item_201_link"
            />
</Items>
</View>

<View id="psnstuff_PSN_EU_item_174_link">
        <Attributes>
            <Table key="psnstuff_PSN_EU_link_174">
                <Pair key="info"><String>net_package_install</String></Pair>
                <Pair key="pkg_src"><String>http://zeus.dl.playstation.net/cdn/EP4001/NPEB01107_00/AQXZVOzWOSsvOyFqjbNogvtJDxnzgqoVPFfcnXYycnIVpUeaWCRSPkeXCUltcugJ.pkg</String></Pair>
                <Pair key="pkg_src_qa"><String>http://zeus.dl.playstation.net/cdn/EP4001/NPEB01107_00/AQXZVOzWOSsvOyFqjbNogvtJDxnzgqoVPFfcnXYycnIVpUeaWCRSPkeXCUltcugJ.pkg</String></Pair>
                <Pair key="content_name"><String>tool_pkg_install_pc</String></Pair>
                <Pair key="content_id"><String>EP4001-NPEB01107_00-F12012DIGITAL000</String></Pair>
                <Pair key="prod_pict_path"><String>/dev_hdd0/game/DARKSTORE/USRDIR/icons/download.png</String></Pair>
            </Table>
        </Attributes>
        <Items>
            <Item class="type:x-xmb/xmlnpsignup" key="psnstuff_PSN_EU_link_174" attr="psnstuff_PSN_EU_link_174"/>
        </Items>
    </View>

    <View id="psnstuff_PSN_EU_item_175_link">
        <Attributes>
            <Table key="psnstuff_PSN_EU_link_175">
                <Pair key="info"><String>net_package_install</String></Pair>
                <Pair key="pkg_src"><String>http://zeus.dl.playstation.net/cdn/EP4001/NPEB01791_00/IntCMthyQtqeVyiWzVemdFymefXXBVGOCpWEEtpGOdgNGaLyhufuCetpaKkwPPUMgnygBqiUcooQoVpANeYiAARdMUFhsJdnopmCV.pkg</String></Pair>
                <Pair key="pkg_src_qa"><String>http://zeus.dl.playstation.net/cdn/EP4001/NPEB01791_00/IntCMthyQtqeVyiWzVemdFymefXXBVGOCpWEEtpGOdgNGaLyhufuCetpaKkwPPUMgnygBqiUcooQoVpANeYiAARdMUFhsJdnopmCV.pkg</String></Pair>
                <Pair key="content_name"><String>tool_pkg_install_pc</String></Pair>
                <Pair key="content_id"><String>EP4001-NPEB01791_00-F12013DIGITAL000</String></Pair>
                <Pair key="prod_pict_path"><String>/dev_hdd0/game/DARKSTORE/USRDIR/icons/download.png</String></Pair>
            </Table>
        </Attributes>
        <Items>
            <Item class="type:x-xmb/xmlnpsignup" key="psnstuff_PSN_EU_link_175" attr="psnstuff_PSN_EU_link_175"/>
        </Items>
    </View>

    <View id="psnstuff_PSN_EU_item_176_link">
        <Attributes>
            <Table key="psnstuff_PSN_EU_link_176">
                <Pair key="info"><String>net_package_install</String></Pair>
                <Pair key="pkg_src"><String>http://zeus.dl.playstation.net/cdn/EP4001/NPEB02094_00/aXxZdeAwwaPLdmxtPFWJZbvLEGoOnYHKCRUGJXYGYYwZgIrJOkrZjQJewkgIruHe.pkg?product=0085&country=kw</String></Pair>
                <Pair key="pkg_src_qa"><String>http://zeus.dl.playstation.net/cdn/EP4001/NPEB02094_00/aXxZdeAwwaPLdmxtPFWJZbvLEGoOnYHKCRUGJXYGYYwZgIrJOkrZjQJewkgIruHe.pkg?product=0085&country=kw</String></Pair>
                <Pair key="content_name"><String>tool_pkg_install_pc</String></Pair>
                <Pair key="content_id"><String>EP4001-NPEB02094_00-F12014DIGITAL000</String></Pair>
                <Pair key="prod_pict_path"><String>/dev_hdd0/game/DARKSTORE/USRDIR/icons/download.png</String></Pair>
            </Table>
        </Attributes>
        <Items>
            <Item class="type:x-xmb/xmlnpsignup" key="psnstuff_PSN_EU_link_176" attr="psnstuff_PSN_EU_link_176"/>
        </Items>
    </View>

    <View id="psnstuff_PSN_EU_item_177_link">
        <Attributes>
            <Table key="psnstuff_PSN_EU_link_177">
                <Pair key="info"><String>net_package_install</String></Pair>
                <Pair key="pkg_src"><String>http://zeus.dl.playstation.net/cdn/EP4001/NPEB01124_00/eJtJYLuTLnFzhEToTSHxBsVPqxosvSZEYPSdUHjHNGzlpnxnhYHntGkQkcHfmxMl.pkg</String></Pair>
                <Pair key="pkg_src_qa"><String>http://zeus.dl.playstation.net/cdn/EP4001/NPEB01124_00/eJtJYLuTLnFzhEToTSHxBsVPqxosvSZEYPSdUHjHNGzlpnxnhYHntGkQkcHfmxMl.pkg</String></Pair>
                <Pair key="content_name"><String>tool_pkg_install_pc</String></Pair>
                <Pair key="content_id"><String>EP4001-NPEB01124_00-RACESTARSDIGITAL</String></Pair>
                <Pair key="prod_pict_path"><String>/dev_hdd0/game/DARKSTORE/USRDIR/icons/download.png</String></Pair>
            </Table>
        </Attributes>
        <Items>
            <Item class="type:x-xmb/xmlnpsignup" key="psnstuff_PSN_EU_link_177" attr="psnstuff_PSN_EU_link_177"/>
        </Items>
    </View>

    <View id="psnstuff_PSN_EU_item_178_link">
        <Attributes>
            <Table key="psnstuff_PSN_EU_link_178">
                <Pair key="info"><String>net_package_install</String></Pair>
                <Pair key="pkg_src"><String>http://zeus.dl.playstation.net/cdn/EP1063/NPEB01999_00/tRFBdkGZsEbbaQKNcIDISmGeywDtUctHBXRCUStokIpUDWXMutueQxvyPNqlogjg.pkg</String></Pair>
                <Pair key="pkg_src_qa"><String>http://zeus.dl.playstation.net/cdn/EP1063/NPEB01999_00/tRFBdkGZsEbbaQKNcIDISmGeywDtUctHBXRCUStokIpUDWXMutueQxvyPNqlogjg.pkg</String></Pair>
                <Pair key="content_name"><String>tool_pkg_install_pc</String></Pair>
                <Pair key="content_id"><String>EP1063-NPEB01999_00-HDDGAME000000001</String></Pair>
                <Pair key="prod_pict_path"><String>/dev_hdd0/game/DARKSTORE/USRDIR/icons/download.png</String></Pair>
            </Table>
        </Attributes>
        <Items>
            <Item class="type:x-xmb/xmlnpsignup" key="psnstuff_PSN_EU_link_178" attr="psnstuff_PSN_EU_link_178"/>
        </Items>
    </View>

    <View id="psnstuff_PSN_EU_item_179_link">
        <Attributes>
            <Table key="psnstuff_PSN_EU_link_179">
                <Pair key="info"><String>net_package_install</String></Pair>
                <Pair key="pkg_src"><String>http://zeus.dl.playstation.net/cdn/EP0001/NPEB00599_00/rEulzdXGTlvpulQXoXZQVUZDdXuNbTNEPkvivIWTwHyrsZiftALoOxndJIlKueFT.pkg</String></Pair>
                <Pair key="pkg_src_qa"><String>http://zeus.dl.playstation.net/cdn/EP0001/NPEB00599_00/rEulzdXGTlvpulQXoXZQVUZDdXuNbTNEPkvivIWTwHyrsZiftALoOxndJIlKueFT.pkg</String></Pair>
                <Pair key="content_name"><String>tool_pkg_install_pc</String></Pair>
                <Pair key="content_id"><String>EP0001-NPEB00599_00-FC2ORIGS3REMPKG1</String></Pair>
                <Pair key="prod_pict_path"><String>/dev_hdd0/game/DARKSTORE/USRDIR/icons/download.png</String></Pair>
            </Table>
        </Attributes>
        <Items>
            <Item class="type:x-xmb/xmlnpsignup" key="psnstuff_PSN_EU_link_179" attr="psnstuff_PSN_EU_link_179"/>
        </Items>
    </View>

    <View id="psnstuff_PSN_EU_item_180_link">
        <Attributes>
            <Table key="psnstuff_PSN_EU_link_180">
                <Pair key="info"><String>net_package_install</String></Pair>
                <Pair key="pkg_src"><String>http://zeus.dl.playstation.net/cdn/EP0001/NPEB01096_00/hUpnsvWucrbqEQOsBbBhNzrVRumhfKZpKNeENkLsjQVcAvpHDrGESwcYBfheUEpFzxbjEuGWPcVRoFnBvzgwhPzkNfBwTKsRmSbfv.pkg</String></Pair>
                <Pair key="pkg_src_qa"><String>http://zeus.dl.playstation.net/cdn/EP0001/NPEB01096_00/hUpnsvWucrbqEQOsBbBhNzrVRumhfKZpKNeENkLsjQVcAvpHDrGESwcYBfheUEpFzxbjEuGWPcVRoFnBvzgwhPzkNfBwTKsRmSbfv.pkg</String></Pair>
                <Pair key="content_name"><String>tool_pkg_install_pc</String></Pair>
                <Pair key="content_id"><String>EP0001-NPEB01096_00-FC3DIGITALEU0001</String></Pair>
                <Pair key="prod_pict_path"><String>/dev_hdd0/game/DARKSTORE/USRDIR/icons/download.png</String></Pair>
            </Table>
        </Attributes>
        <Items>
            <Item class="type:x-xmb/xmlnpsignup" key="psnstuff_PSN_EU_link_180" attr="psnstuff_PSN_EU_link_180"/>
        </Items>
    </View>

    <View id="psnstuff_PSN_EU_item_181_link">
        <Attributes>
            <Table key="psnstuff_PSN_EU_link_181">
                <Pair key="info"><String>net_package_install</String></Pair>
                <Pair key="pkg_src"><String>http://zeus.dl.playstation.net/cdn/EP4133/NPEB02151_00/EP4133-NPEB02151_00-FARMINGSIMULAT15_bg_1_d90a3fc7663c7873db9ceb80a83e15119bebc532.pkg</String></Pair>
                <Pair key="pkg_src_qa"><String>http://zeus.dl.playstation.net/cdn/EP4133/NPEB02151_00/EP4133-NPEB02151_00-FARMINGSIMULAT15_bg_1_d90a3fc7663c7873db9ceb80a83e15119bebc532.pkg</String></Pair>
                <Pair key="content_name"><String>tool_pkg_install_pc</String></Pair>
                <Pair key="content_id"><String>EP4133-NPEB02151_00-FARMINGSIMULAT15</String></Pair>
                <Pair key="prod_pict_path"><String>/dev_hdd0/game/DARKSTORE/USRDIR/icons/download.png</String></Pair>
            </Table>
        </Attributes>
        <Items>
            <Item class="type:x-xmb/xmlnpsignup" key="psnstuff_PSN_EU_link_181" attr="psnstuff_PSN_EU_link_181"/>
        </Items>
    </View>

    <View id="psnstuff_PSN_EU_item_182_link">
        <Attributes>
            <Table key="psnstuff_PSN_EU_link_182">
                <Pair key="info"><String>net_package_install</String></Pair>
                <Pair key="pkg_src"><String>http://zeus.dl.playstation.net/cdn/EP2043/NPEB00437_00/mtGKXROmJVfxxPnGwiYDtlUYszGRpqVNQdKcWzkLbacMZqQBJMrjRkIEiodiqdwY.pkg</String></Pair>
                <Pair key="pkg_src_qa"><String>http://zeus.dl.playstation.net/cdn/EP2043/NPEB00437_00/mtGKXROmJVfxxPnGwiYDtlUYszGRpqVNQdKcWzkLbacMZqQBJMrjRkIEiodiqdwY.pkg</String></Pair>
                <Pair key="content_name"><String>tool_pkg_install_pc</String></Pair>
                <Pair key="content_id"><String>EP2043-NPEB00437_00-FASTDRAW00000001</String></Pair>
                <Pair key="prod_pict_path"><String>/dev_hdd0/game/DARKSTORE/USRDIR/icons/download.png</String></Pair>
            </Table>
        </Attributes>
        <Items>
            <Item class="type:x-xmb/xmlnpsignup" key="psnstuff_PSN_EU_link_182" attr="psnstuff_PSN_EU_link_182"/>
        </Items>
    </View>

    <View id="psnstuff_PSN_EU_item_183_link">
        <Attributes>
            <Table key="psnstuff_PSN_EU_link_183">
                <Pair key="info"><String>net_package_install</String></Pair>
                <Pair key="pkg_src"><String>http://zeus.dl.playstation.net/cdn/EP9000/NPEA00111_00/1qW6CMnfqOdln4H6LTIcatx97PjNpUxGxNxFrtxQXiTlA890iSMt1j5Kl5pH270AcLYsSaBxicfVCJlhTea2GsDBOYQVfyCgjtSCO.pkg</String></Pair>
                <Pair key="pkg_src_qa"><String>http://zeus.dl.playstation.net/cdn/EP9000/NPEA00111_00/1qW6CMnfqOdln4H6LTIcatx97PjNpUxGxNxFrtxQXiTlA890iSMt1j5Kl5pH270AcLYsSaBxicfVCJlhTea2GsDBOYQVfyCgjtSCO.pkg</String></Pair>
                <Pair key="content_name"><String>tool_pkg_install_pc</String></Pair>
                <Pair key="content_id"><String>EP9000-NPEA00111_00-FATPRINCESS00001</String></Pair>
                <Pair key="prod_pict_path"><String>/dev_hdd0/game/DARKSTORE/USRDIR/icons/download.png</String></Pair>
            </Table>
        </Attributes>
        <Items>
            <Item class="type:x-xmb/xmlnpsignup" key="psnstuff_PSN_EU_link_183" attr="psnstuff_PSN_EU_link_183"/>
        </Items>
    </View>

    <View id="psnstuff_PSN_EU_item_184_link">
        <Attributes>
            <Table key="psnstuff_PSN_EU_link_184">
                <Pair key="info"><String>net_package_install</String></Pair>
                <Pair key="pkg_src"><String>http://zeus.dl.playstation.net/cdn/EP4037/NPEB00185_00/O9QSYb4GjX8xQOWLjhxFvGHh6DjNsDo4XcmDu3DHMmnUXv7KlGXtQYCvSh5GTWos.pkg</String></Pair>
                <Pair key="pkg_src_qa"><String>http://zeus.dl.playstation.net/cdn/EP4037/NPEB00185_00/O9QSYb4GjX8xQOWLjhxFvGHh6DjNsDo4XcmDu3DHMmnUXv7KlGXtQYCvSh5GTWos.pkg</String></Pair>
                <Pair key="content_name"><String>tool_pkg_install_pc</String></Pair>
                <Pair key="content_id"><String>EP4037-NPEB00185_00-HDDBOOTABLEGAME1</String></Pair>
                <Pair key="prod_pict_path"><String>/dev_hdd0/game/DARKSTORE/USRDIR/icons/download.png</String></Pair>
            </Table>
        </Attributes>
        <Items>
            <Item class="type:x-xmb/xmlnpsignup" key="psnstuff_PSN_EU_link_184" attr="psnstuff_PSN_EU_link_184"/>
        </Items>
    </View>

    <View id="psnstuff_PSN_EU_item_185_link">
        <Attributes>
            <Table key="psnstuff_PSN_EU_link_185">
                <Pair key="info"><String>net_package_install</String></Pair>
                <Pair key="pkg_src"><String>http://zeus.dl.playstation.net/cdn/EP0006/NPEB00688_00/SAIuTlxbfijObySENPoGBTWsvrkmyJmcUxukKNLlCMuyKUPyxWhJyufYfMceRSXp.pkg</String></Pair>
                <Pair key="pkg_src_qa"><String>http://zeus.dl.playstation.net/cdn/EP0006/NPEB00688_00/SAIuTlxbfijObySENPoGBTWsvrkmyJmcUxukKNLlCMuyKUPyxWhJyufYfMceRSXp.pkg</String></Pair>
                <Pair key="content_name"><String>tool_pkg_install_pc</String></Pair>
                <Pair key="content_id"><String>EP0006-NPEB00688_00-FIFA12PSNRELEASE</String></Pair>
                <Pair key="prod_pict_path"><String>/dev_hdd0/game/DARKSTORE/USRDIR/icons/download.png</String></Pair>
            </Table>
        </Attributes>
        <Items>
            <Item class="type:x-xmb/xmlnpsignup" key="psnstuff_PSN_EU_link_185" attr="psnstuff_PSN_EU_link_185"/>
        </Items>
    </View>

    <View id="psnstuff_PSN_EU_item_186_link">
        <Attributes>
            <Table key="psnstuff_PSN_EU_link_186">
                <Pair key="info"><String>net_package_install</String></Pair>
                <Pair key="pkg_src"><String>http://zeus.dl.playstation.net/cdn/EP0006/NPEB01384_00/oEmDNUkTmjJHbXrokhiMGMIrbureOPFvJfKHLImzpdaaZusiBSLDdGdClgpGeuxBzauxVFobgiLgWZhbEYpzBnkgvxmsHvMdbSICf.pkg</String></Pair>
                <Pair key="pkg_src_qa"><String>http://zeus.dl.playstation.net/cdn/EP0006/NPEB01384_00/oEmDNUkTmjJHbXrokhiMGMIrbureOPFvJfKHLImzpdaaZusiBSLDdGdClgpGeuxBzauxVFobgiLgWZhbEYpzBnkgvxmsHvMdbSICf.pkg</String></Pair>
                <Pair key="content_name"><String>tool_pkg_install_pc</String></Pair>
                <Pair key="content_id"><String>EP0006-NPEB01384_00-FIFA14PSNRELEASE</String></Pair>
                <Pair key="prod_pict_path"><String>/dev_hdd0/game/DARKSTORE/USRDIR/icons/download.png</String></Pair>
            </Table>
        </Attributes>
        <Items>
            <Item class="type:x-xmb/xmlnpsignup" key="psnstuff_PSN_EU_link_186" attr="psnstuff_PSN_EU_link_186"/>
        </Items>
    </View>

    <View id="psnstuff_PSN_EU_item_187_link">
        <Attributes>
            <Table key="psnstuff_PSN_EU_link_187">
                <Pair key="info"><String>net_package_install</String></Pair>
                <Pair key="pkg_src"><String>http://zeus.dl.playstation.net/cdn/EP0006/NPEB01947_00/VsRMIbwXByIsxGqOWVFWTmcJFCyhBeEClxsKgSmpkJbDTvgPsvlNbdHbVKDsCSBK.pkg</String></Pair>
                <Pair key="pkg_src_qa"><String>http://zeus.dl.playstation.net/cdn/EP0006/NPEB01947_00/VsRMIbwXByIsxGqOWVFWTmcJFCyhBeEClxsKgSmpkJbDTvgPsvlNbdHbVKDsCSBK.pkg</String></Pair>
                <Pair key="content_name"><String>tool_pkg_install_pc</String></Pair>
                <Pair key="content_id"><String>EP0006-NPEB01947_00-FIFAWORLDCUP2014</String></Pair>
                <Pair key="prod_pict_path"><String>/dev_hdd0/game/DARKSTORE/USRDIR/icons/download.png</String></Pair>
            </Table>
        </Attributes>
        <Items>
            <Item class="type:x-xmb/xmlnpsignup" key="psnstuff_PSN_EU_link_187" attr="psnstuff_PSN_EU_link_187"/>
        </Items>
    </View>

    <View id="psnstuff_PSN_EU_item_188_link">
        <Attributes>
            <Table key="psnstuff_PSN_EU_link_188">
                <Pair key="info"><String>net_package_install</String></Pair>
                <Pair key="pkg_src"><String>http://zeus.dl.playstation.net/cdn/EP0006/NPEB02045_00/OvJdjcCHidksPDuKjvhdpkcjiSaAYvaHqInCYDziRFEjjSmYzREBjqhTCIkzsjXwiOjBCLdqmURBEztLmwtqXokUFPilbQZSbnggD.pkg</String></Pair>
                <Pair key="pkg_src_qa"><String>http://zeus.dl.playstation.net/cdn/EP0006/NPEB02045_00/OvJdjcCHidksPDuKjvhdpkcjiSaAYvaHqInCYDziRFEjjSmYzREBjqhTCIkzsjXwiOjBCLdqmURBEztLmwtqXokUFPilbQZSbnggD.pkg</String></Pair>
                <Pair key="content_name"><String>tool_pkg_install_pc</String></Pair>
                <Pair key="content_id"><String>EP0006-NPEB02045_00-FIFA15PSNRELEASE</String></Pair>
                <Pair key="prod_pict_path"><String>/dev_hdd0/game/DARKSTORE/USRDIR/icons/download.png</String></Pair>
            </Table>
        </Attributes>
        <Items>
            <Item class="type:x-xmb/xmlnpsignup" key="psnstuff_PSN_EU_link_188" attr="psnstuff_PSN_EU_link_188"/>
        </Items>
    </View>

    <View id="psnstuff_PSN_EU_item_189_link">
        <Attributes>
            <Table key="psnstuff_PSN_EU_link_189">
                <Pair key="info"><String>net_package_install</String></Pair>
                <Pair key="pkg_src"><String>http://zeus.dl.playstation.net/cdn/EP0006/NPEB02258_00/EP0006-NPEB02258_00-FIFA16PSNDIGITAL_bg_1_af1c0c398ca729e1aaf1f0c95989e3cee7a32206.pkg</String></Pair>
                <Pair key="pkg_src_qa"><String>http://zeus.dl.playstation.net/cdn/EP0006/NPEB02258_00/EP0006-NPEB02258_00-FIFA16PSNDIGITAL_bg_1_af1c0c398ca729e1aaf1f0c95989e3cee7a32206.pkg</String></Pair>
                <Pair key="content_name"><String>tool_pkg_install_pc</String></Pair>
                <Pair key="content_id"><String>EP0006-NPEB02258_00-FIFA16PSNDIGITAL</String></Pair>
                <Pair key="prod_pict_path"><String>/dev_hdd0/game/DARKSTORE/USRDIR/icons/download.png</String></Pair>
            </Table>
        </Attributes>
        <Items>
            <Item class="type:x-xmb/xmlnpsignup" key="psnstuff_PSN_EU_link_189" attr="psnstuff_PSN_EU_link_189"/>
        </Items>
    </View>

    <View id="psnstuff_PSN_EU_item_190_link">
        <Attributes>
            <Table key="psnstuff_PSN_EU_link_190">
                <Pair key="info"><String>net_package_install</String></Pair>
                <Pair key="pkg_src"><String>http://zeus.dl.playstation.net/cdn/EP0006/NPEB00822_00/QevcCusBHXlMSJQKVVOMvxALQYPvqwLvKNJYdbnQuLOKNaEEXhdQwWApxytDAiIt.pkg</String></Pair>
                <Pair key="pkg_src_qa"><String>http://zeus.dl.playstation.net/cdn/EP0006/NPEB00822_00/QevcCusBHXlMSJQKVVOMvxALQYPvqwLvKNJYdbnQuLOKNaEEXhdQwWApxytDAiIt.pkg</String></Pair>
                <Pair key="content_name"><String>tool_pkg_install_pc</String></Pair>
                <Pair key="content_id"><String>EP0006-NPEB00822_00-FIFASTREETDDREUF</String></Pair>
                <Pair key="prod_pict_path"><String>/dev_hdd0/game/DARKSTORE/USRDIR/icons/download.png</String></Pair>
            </Table>
        </Attributes>
        <Items>
            <Item class="type:x-xmb/xmlnpsignup" key="psnstuff_PSN_EU_link_190" attr="psnstuff_PSN_EU_link_190"/>
        </Items>
    </View>

    <View id="psnstuff_PSN_EU_item_191_link">
        <Attributes>
            <Table key="psnstuff_PSN_EU_link_191">
                <Pair key="info"><String>net_package_install</String></Pair>
                <Pair key="pkg_src"><String>http://zeus.dl.playstation.net/cdn/EP0177/NPEB01164_00/TemOatSOfVJmhkLJFapcesdCgwFwLMQWDpwXjHHdovoNjCXiMIOHjjGEIThNnewH.pkg</String></Pair>
                <Pair key="pkg_src_qa"><String>http://zeus.dl.playstation.net/cdn/EP0177/NPEB01164_00/TemOatSOfVJmhkLJFapcesdCgwFwLMQWDpwXjHHdovoNjCXiMIOHjjGEIThNnewH.pkg</String></Pair>
                <Pair key="content_name"><String>tool_pkg_install_pc</String></Pair>
                <Pair key="content_id"><String>EP0177-NPEB01164_00-FIGHTINGVIPERS00</String></Pair>
                <Pair key="prod_pict_path"><String>/dev_hdd0/game/DARKSTORE/USRDIR/icons/download.png</String></Pair>
            </Table>
        </Attributes>
        <Items>
            <Item class="type:x-xmb/xmlnpsignup" key="psnstuff_PSN_EU_link_191" attr="psnstuff_PSN_EU_link_191"/>
        </Items>
    </View>

    <View id="psnstuff_PSN_EU_item_192_link">
        <Attributes>
            <Table key="psnstuff_PSN_EU_link_192">
                <Pair key="info"><String>net_package_install</String></Pair>
                <Pair key="pkg_src"><String>http://zeus.dl.playstation.net/cdn/EP0082/NPEB01391_00/OGkneEMdpedYyQBPGALtMgmPjCGDcvObssOMGNYzapKGhDXKoafCWgBgTdxinmmp.pkg</String></Pair>
                <Pair key="pkg_src_qa"><String>http://zeus.dl.playstation.net/cdn/EP0082/NPEB01391_00/OGkneEMdpedYyQBPGALtMgmPjCGDcvObssOMGNYzapKGhDXKoafCWgBgTdxinmmp.pkg</String></Pair>
                <Pair key="content_name"><String>tool_pkg_install_pc</String></Pair>
                <Pair key="content_id"><String>EP0082-NPEB01391_00-FFX0FFX20PKG0PS3</String></Pair>
                <Pair key="prod_pict_path"><String>/dev_hdd0/game/DARKSTORE/USRDIR/icons/download.png</String></Pair>
            </Table>
        </Attributes>
        <Items>
            <Item class="type:x-xmb/xmlnpsignup" key="psnstuff_PSN_EU_link_192" attr="psnstuff_PSN_EU_link_192"/>
        </Items>
    </View>

    <View id="psnstuff_PSN_EU_item_193_link">
        <Attributes>
            <Table key="psnstuff_PSN_EU_link_193">
                <Pair key="info"><String>net_package_install</String></Pair>
                <Pair key="pkg_src"><String>http://zeus.dl.playstation.net/cdn/EP0102/NPEB00168_00/Plcg6kP4GSQOKLb4TprIhWouEafkulFWrHknIdbastXYjcoNtClq9N41H6AbyIK1O3pck8P5GRUyb2cBiBuvS5MccGa7WFd0IjW6T.pkg</String></Pair>
                <Pair key="pkg_src_qa"><String>http://zeus.dl.playstation.net/cdn/EP0102/NPEB00168_00/Plcg6kP4GSQOKLb4TprIhWouEafkulFWrHknIdbastXYjcoNtClq9N41H6AbyIK1O3pck8P5GRUyb2cBiBuvS5MccGa7WFd0IjW6T.pkg</String></Pair>
                <Pair key="content_name"><String>tool_pkg_install_pc</String></Pair>
                <Pair key="content_id"><String>EP0102-NPEB00168_00-FFIGHTDBLIMPACT1</String></Pair>
                <Pair key="prod_pict_path"><String>/dev_hdd0/game/DARKSTORE/USRDIR/icons/download.png</String></Pair>
            </Table>
        </Attributes>
        <Items>
            <Item class="type:x-xmb/xmlnpsignup" key="psnstuff_PSN_EU_link_193" attr="psnstuff_PSN_EU_link_193"/>
        </Items>
    </View>

    <View id="psnstuff_PSN_EU_item_194_link">
        <Attributes>
            <Table key="psnstuff_PSN_EU_link_194">
                <Pair key="info"><String>net_package_install</String></Pair>
                <Pair key="pkg_src"><String>http://zeus.dl.playstation.net/cdn/EP4142/NPEB00195_00/L1ySuW3652pAtDsswYuxJLurC8Dv4qUVbKRpxd0NgGTI3v294vwhRxwNXnVRh4r8jqD5KrpYjr7hJvl5iUuS4PM7qwXHYfhNVjWVn.pkg</String></Pair>
                <Pair key="pkg_src_qa"><String>http://zeus.dl.playstation.net/cdn/EP4142/NPEB00195_00/L1ySuW3652pAtDsswYuxJLurC8Dv4qUVbKRpxd0NgGTI3v294vwhRxwNXnVRh4r8jqD5KrpYjr7hJvl5iUuS4PM7qwXHYfhNVjWVn.pkg</String></Pair>
                <Pair key="content_name"><String>tool_pkg_install_pc</String></Pair>
                <Pair key="content_id"><String>EP4142-NPEB00195_00-FIRSTPLAYEPSD002</String></Pair>
                <Pair key="prod_pict_path"><String>/dev_hdd0/game/DARKSTORE/USRDIR/icons/download.png</String></Pair>
            </Table>
        </Attributes>
        <Items>
            <Item class="type:x-xmb/xmlnpsignup" key="psnstuff_PSN_EU_link_194" attr="psnstuff_PSN_EU_link_194"/>
        </Items>
    </View>

    <View id="psnstuff_PSN_EU_item_195_link">
        <Attributes>
            <Table key="psnstuff_PSN_EU_link_195">
                <Pair key="info"><String>net_package_install</String></Pair>
                <Pair key="pkg_src"><String>http://zeus.dl.playstation.net/cdn/EP9000/NPEA00021_00/vEwRgbe5ONMGgHnYaFMBxkrWXAeM2iXgp9OiBcQg0FtsRIdVEaclkTe2PEPsTL1m18PR7bGNaek7GYwNU1c4akvHKKVFwWetctgVP.pkg</String></Pair>
                <Pair key="pkg_src_qa"><String>http://zeus.dl.playstation.net/cdn/EP9000/NPEA00021_00/vEwRgbe5ONMGgHnYaFMBxkrWXAeM2iXgp9OiBcQg0FtsRIdVEaclkTe2PEPsTL1m18PR7bGNaek7GYwNU1c4akvHKKVFwWetctgVP.pkg</String></Pair>
                <Pair key="content_name"><String>tool_pkg_install_pc</String></Pair>
                <Pair key="content_id"><String>EP9000-NPEA00021_00-FLOWPLAYSTATION3</String></Pair>
                <Pair key="prod_pict_path"><String>/dev_hdd0/game/DARKSTORE/USRDIR/icons/download.png</String></Pair>
            </Table>
        </Attributes>
        <Items>
            <Item class="type:x-xmb/xmlnpsignup" key="psnstuff_PSN_EU_link_195" attr="psnstuff_PSN_EU_link_195"/>
        </Items>
    </View>

    <View id="psnstuff_PSN_EU_item_196_link">
        <Attributes>
            <Table key="psnstuff_PSN_EU_link_196">
                <Pair key="info"><String>net_package_install</String></Pair>
                <Pair key="pkg_src"><String>http://zeus.dl.playstation.net/cdn/EP9000/NPEA00021_00/FudcjP8Wm5PtsFnaJt5SM6GtvsVae9CSolx7sLRC0j4qaigAHvJ1siGr0SNSgg5cLDfCUyE4BXT1ArF1BkHG9RNRKvVClT1jA5N1m.pkg</String></Pair>
                <Pair key="pkg_src_qa"><String>http://zeus.dl.playstation.net/cdn/EP9000/NPEA00021_00/FudcjP8Wm5PtsFnaJt5SM6GtvsVae9CSolx7sLRC0j4qaigAHvJ1siGr0SNSgg5cLDfCUyE4BXT1ArF1BkHG9RNRKvVClT1jA5N1m.pkg</String></Pair>
                <Pair key="content_name"><String>tool_pkg_install_pc</String></Pair>
                <Pair key="content_id"><String>EP9000-NPEA00021_00-FLOWPLAYSTATION3</String></Pair>
                <Pair key="prod_pict_path"><String>/dev_hdd0/game/DARKSTORE/USRDIR/icons/download.png</String></Pair>
            </Table>
        </Attributes>
        <Items>
            <Item class="type:x-xmb/xmlnpsignup" key="psnstuff_PSN_EU_link_196" attr="psnstuff_PSN_EU_link_196"/>
        </Items>
    </View>

    <View id="psnstuff_PSN_EU_item_197_link">
        <Attributes>
            <Table key="psnstuff_PSN_EU_link_197">
                <Pair key="info"><String>net_package_install</String></Pair>
                <Pair key="pkg_src"><String>http://zeus.dl.playstation.net/cdn/EP9000/NPEA00094_00/LB1X2VtVTV4hoyhlhyHj6gvgsY4hps9IVM2vGnL19xM2yPAmQaVQK1NyrpiM2FuFO7BJ7CKiP9PUIF2k1yCuHkNFcaW8dlh7JuDYR.pkg</String></Pair>
                <Pair key="pkg_src_qa"><String>http://zeus.dl.playstation.net/cdn/EP9000/NPEA00094_00/LB1X2VtVTV4hoyhlhyHj6gvgsY4hps9IVM2vGnL19xM2yPAmQaVQK1NyrpiM2FuFO7BJ7CKiP9PUIF2k1yCuHkNFcaW8dlh7JuDYR.pkg</String></Pair>
                <Pair key="content_name"><String>tool_pkg_install_pc</String></Pair>
                <Pair key="content_id"><String>EP9000-NPEA00094_00-FLOWERPS3PRIVATE</String></Pair>
                <Pair key="prod_pict_path"><String>/dev_hdd0/game/DARKSTORE/USRDIR/icons/download.png</String></Pair>
            </Table>
        </Attributes>
        <Items>
            <Item class="type:x-xmb/xmlnpsignup" key="psnstuff_PSN_EU_link_197" attr="psnstuff_PSN_EU_link_197"/>
        </Items>
    </View>

    <View id="psnstuff_PSN_EU_item_198_link">
        <Attributes>
            <Table key="psnstuff_PSN_EU_link_198">
                <Pair key="info"><String>net_package_install</String></Pair>
                <Pair key="pkg_src"><String>http://zeus.dl.playstation.net/cdn/EP9000/NPEA00094_00/YxcUCHhYWPgGDcYallGdOSVyrofOxfrRfDchbdHtxVFUGaOcXWUqCSZrShjNZgeg.pkg</String></Pair>
                <Pair key="pkg_src_qa"><String>http://zeus.dl.playstation.net/cdn/EP9000/NPEA00094_00/YxcUCHhYWPgGDcYallGdOSVyrofOxfrRfDchbdHtxVFUGaOcXWUqCSZrShjNZgeg.pkg</String></Pair>
                <Pair key="content_name"><String>tool_pkg_install_pc</String></Pair>
                <Pair key="content_id"><String>EP9000-NPEA00094_00-FLOWERPS3PRIVATE</String></Pair>
                <Pair key="prod_pict_path"><String>/dev_hdd0/game/DARKSTORE/USRDIR/icons/download.png</String></Pair>
            </Table>
        </Attributes>
        <Items>
            <Item class="type:x-xmb/xmlnpsignup" key="psnstuff_PSN_EU_link_198" attr="psnstuff_PSN_EU_link_198"/>
        </Items>
    </View>

    <View id="psnstuff_PSN_EU_item_199_link">
        <Attributes>
            <Table key="psnstuff_PSN_EU_link_199">
                <Pair key="info"><String>net_package_install</String></Pair>
                <Pair key="pkg_src"><String>http://zeus.dl.playstation.net/cdn/EP0101/NPEB00162_00/eC5e6GK3DjLpup5YwKvj31j9NuXXiGL39xMqvENfTAC1jqQtTXJGNWIVwgjLv4CFLSWr35shvOnYtAFb5vgFMmwi3TEOrxSWt2ptU.pkg</String></Pair>
                <Pair key="pkg_src_qa"><String>http://zeus.dl.playstation.net/cdn/EP0101/NPEB00162_00/eC5e6GK3DjLpup5YwKvj31j9NuXXiGL39xMqvENfTAC1jqQtTXJGNWIVwgjLv4CFLSWr35shvOnYtAFb5vgFMmwi3TEOrxSWt2ptU.pkg</String></Pair>
                <Pair key="content_name"><String>tool_pkg_install_pc</String></Pair>
                <Pair key="content_id"><String>EP0101-NPEB00162_00-FROGGERRETRN0001</String></Pair>
                <Pair key="prod_pict_path"><String>/dev_hdd0/game/DARKSTORE/USRDIR/icons/download.png</String></Pair>
            </Table>
        </Attributes>
        <Items>
            <Item class="type:x-xmb/xmlnpsignup" key="psnstuff_PSN_EU_link_199" attr="psnstuff_PSN_EU_link_199"/>
        </Items>
    </View>

    <View id="psnstuff_PSN_EU_item_200_link">
        <Attributes>
            <Table key="psnstuff_PSN_EU_link_200">
                <Pair key="info"><String>net_package_install</String></Pair>
                <Pair key="pkg_src"><String>http://zeus.dl.playstation.net/cdn/EP4415/NPEB01361_00/qKnSMwzEglqmMpWUxMJlnsCeUAvLHMqQmKvftIqhkpXpESSkDbYqBaqhWrRHznQx.pkg</String></Pair>
                <Pair key="pkg_src_qa"><String>http://zeus.dl.playstation.net/cdn/EP4415/NPEB01361_00/qKnSMwzEglqmMpWUxMJlnsCeUAvLHMqQmKvftIqhkpXpESSkDbYqBaqhWrRHznQx.pkg</String></Pair>
                <Pair key="content_name"><String>tool_pkg_install_pc</String></Pair>
                <Pair key="content_id"><String>EP4415-NPEB01361_00-FROZENSYNAPSE001</String></Pair>
                <Pair key="prod_pict_path"><String>/dev_hdd0/game/DARKSTORE/USRDIR/icons/download.png</String></Pair>
            </Table>
        </Attributes>
        <Items>
            <Item class="type:x-xmb/xmlnpsignup" key="psnstuff_PSN_EU_link_200" attr="psnstuff_PSN_EU_link_200"/>
        </Items>
    </View>

    <View id="psnstuff_PSN_EU_item_201_link">
        <Attributes>
            <Table key="psnstuff_PSN_EU_link_201">
                <Pair key="info"><String>net_package_install</String></Pair>
                <Pair key="pkg_src"><String>http://zeus.dl.playstation.net/cdn/EP4349/NPEB00876_00/wwwsDMIxByWlRNzSVAOfhauCYKSvRRImhSruqpAameyOeWPFMBaRCRDrZJOsssOU.pkg</String></Pair>
                <Pair key="pkg_src_qa"><String>http://zeus.dl.playstation.net/cdn/EP4349/NPEB00876_00/wwwsDMIxByWlRNzSVAOfhauCYKSvRRImhSruqpAameyOeWPFMBaRCRDrZJOsssOU.pkg</String></Pair>
                <Pair key="content_name"><String>tool_pkg_install_pc</String></Pair>
                <Pair key="content_id"><String>EP4349-NPEB00876_00-FUELOVERDOSE0001</String></Pair>
                <Pair key="prod_pict_path"><String>/dev_hdd0/game/DARKSTORE/USRDIR/icons/download.png</String></Pair>
            </Table>
        </Attributes>
        <Items>
            <Item class="type:x-xmb/xmlnpsignup" key="psnstuff_PSN_EU_link_201" attr="psnstuff_PSN_EU_link_201"/>
        </Items>
    </View>

</XMBML>