<XMBML version="1.0">
	<View id="T_games">
		<Attributes>
			<Table key="psnstuff_PSN_JP_item_189">
				<Pair key="icon"><String>/dev_hdd0/game/DARKSTORE/USRDIR/icons/download.png</String></Pair>
				<Pair key="title"><String>Tales of Symphonia</String></Pair>
				<Pair key="info"><String>NPJB00416 - N/A Mb</String></Pair>
				<Pair key="ingame"><String>disable</String></Pair>
			</Table>
			<Table key="psnstuff_PSN_JP_item_190">
				<Pair key="icon"><String>/dev_hdd0/game/DARKSTORE/USRDIR/icons/download.png</String></Pair>
				<Pair key="title"><String>Tales of Symphonia: Ratatosk no Kishi</String></Pair>
				<Pair key="info"><String>NPJB00421 - N/A Mb</String></Pair>
				<Pair key="ingame"><String>disable</String></Pair>
			</Table>
			<Table key="psnstuff_PSN_JP_item_191">
				<Pair key="icon"><String>/dev_hdd0/game/DARKSTORE/USRDIR/icons/download.png</String></Pair>
				<Pair key="title"><String>Tank Battles</String></Pair>
				<Pair key="info"><String>NPJB90228 - 102.52 Mb</String></Pair>
				<Pair key="ingame"><String>disable</String></Pair>
			</Table>
			<Table key="psnstuff_PSN_JP_item_192">
				<Pair key="icon"><String>/dev_hdd0/game/DARKSTORE/USRDIR/icons/download.png</String></Pair>
				<Pair key="title"><String>Tekken Revolution</String></Pair>
				<Pair key="info"><String>NPJB00404 - 1914.42 Mb</String></Pair>
				<Pair key="ingame"><String>disable</String></Pair>
			</Table>
			<Table key="psnstuff_PSN_JP_item_193">
				<Pair key="icon"><String>/dev_hdd0/game/DARKSTORE/USRDIR/icons/download.png</String></Pair>
				<Pair key="title"><String>Tekken Tag Tournament 2</String></Pair>
				<Pair key="info"><String>NPJB00236 - 17530.39 Mb</String></Pair>
				<Pair key="ingame"><String>disable</String></Pair>
			</Table>
			<Table key="psnstuff_PSN_JP_item_194">
				<Pair key="icon"><String>/dev_hdd0/game/DARKSTORE/USRDIR/icons/download.png</String></Pair>
				<Pair key="title"><String>Terraria</String></Pair>
				<Pair key="info"><String>NPJB00383 - 48.59 Mb</String></Pair>
				<Pair key="ingame"><String>disable</String></Pair>
			</Table>
			<Table key="psnstuff_PSN_JP_item_195">
				<Pair key="icon"><String>/dev_hdd0/game/DARKSTORE/USRDIR/icons/download.png</String></Pair>
				<Pair key="title"><String>Tetris</String></Pair>
				<Pair key="info"><String>NPJB00136 - 74.80 Mb</String></Pair>
				<Pair key="ingame"><String>disable</String></Pair>
			</Table>
			<Table key="psnstuff_PSN_JP_item_196">
				<Pair key="icon"><String>/dev_hdd0/game/DARKSTORE/USRDIR/icons/download.png</String></Pair>
				<Pair key="title"><String>The Cave</String></Pair>
				<Pair key="info"><String>NPJB00317 - 1025.72 Mb</String></Pair>
				<Pair key="ingame"><String>disable</String></Pair>
			</Table>
			<Table key="psnstuff_PSN_JP_item_197">
				<Pair key="icon"><String>/dev_hdd0/game/DARKSTORE/USRDIR/icons/download.png</String></Pair>
				<Pair key="title"><String>The Darkness II</String></Pair>
				<Pair key="info"><String>NPJB00205 - 5118.39 Mb</String></Pair>
				<Pair key="ingame"><String>disable</String></Pair>
			</Table>
			<Table key="psnstuff_PSN_JP_item_198">
				<Pair key="icon"><String>/dev_hdd0/game/DARKSTORE/USRDIR/icons/download.png</String></Pair>
				<Pair key="title"><String>The Evil Within (Psycho Break)</String></Pair>
				<Pair key="info"><String>NPJB00615 - 6534.62 Mb</String></Pair>
				<Pair key="ingame"><String>disable</String></Pair>
			</Table>
			<Table key="psnstuff_PSN_JP_item_199">
				<Pair key="icon"><String>/dev_hdd0/game/DARKSTORE/USRDIR/icons/download.png</String></Pair>
				<Pair key="title"><String>The Fancy Pants Adventures</String></Pair>
				<Pair key="info"><String>NPJB00113 - 329.45 Mb</String></Pair>
				<Pair key="ingame"><String>disable</String></Pair>
			</Table>
			<Table key="psnstuff_PSN_JP_item_200">
				<Pair key="icon"><String>/dev_hdd0/game/DARKSTORE/USRDIR/icons/download.png</String></Pair>
				<Pair key="title"><String>The Guided Fate Paradox</String></Pair>
				<Pair key="info"><String>NPJB00350 - 2905.66 Mb</String></Pair>
				<Pair key="ingame"><String>disable</String></Pair>
			</Table>
			<Table key="psnstuff_PSN_JP_item_201">
				<Pair key="icon"><String>/dev_hdd0/game/DARKSTORE/USRDIR/icons/download.png</String></Pair>
				<Pair key="title"><String>THE iDOLM@STER 2</String></Pair>
				<Pair key="info"><String>NPJB00337 - N/A Mb</String></Pair>
				<Pair key="ingame"><String>disable</String></Pair>
			</Table>
			<Table key="psnstuff_PSN_JP_item_202">
				<Pair key="icon"><String>/dev_hdd0/game/DARKSTORE/USRDIR/icons/download.png</String></Pair>
				<Pair key="title"><String>THE iDOLM@STER ONE FOR ALL</String></Pair>
				<Pair key="info"><String>NPJB00611 - N/A Mb</String></Pair>
				<Pair key="ingame"><String>disable</String></Pair>
			</Table>
			<Table key="psnstuff_PSN_JP_item_203">
				<Pair key="icon"><String>/dev_hdd0/game/DARKSTORE/USRDIR/icons/download.png</String></Pair>
				<Pair key="title"><String>THE KING OF FIGHTERS XIII</String></Pair>
				<Pair key="info"><String>NPJB00229 - 2255.87 Mb</String></Pair>
				<Pair key="ingame"><String>disable</String></Pair>
			</Table>
			<Table key="psnstuff_PSN_JP_item_204">
				<Pair key="icon"><String>/dev_hdd0/game/DARKSTORE/USRDIR/icons/download.png</String></Pair>
				<Pair key="title"><String>The Last Guy - Japan Premium</String></Pair>
				<Pair key="info"><String>NPJA00035 - 312.65 Mb</String></Pair>
				<Pair key="ingame"><String>disable</String></Pair>
			</Table>
			<Table key="psnstuff_PSN_JP_item_205">
				<Pair key="icon"><String>/dev_hdd0/game/DARKSTORE/USRDIR/icons/download.png</String></Pair>
				<Pair key="title"><String>The Legend of Heroes: Trails of Cold Steel</String></Pair>
				<Pair key="info"><String>NPJB00409 - 3511.80 Mb</String></Pair>
				<Pair key="ingame"><String>disable</String></Pair>
			</Table>
			<Table key="psnstuff_PSN_JP_item_206">
				<Pair key="icon"><String>/dev_hdd0/game/DARKSTORE/USRDIR/icons/download.png</String></Pair>
				<Pair key="title"><String>The Legend of Heroes: Trails of Cold Steel II</String></Pair>
				<Pair key="info"><String>NPJB00602 - N/A Mb</String></Pair>
				<Pair key="ingame"><String>disable</String></Pair>
			</Table>
			<Table key="psnstuff_PSN_JP_item_207">
				<Pair key="icon"><String>/dev_hdd0/game/DARKSTORE/USRDIR/icons/download.png</String></Pair>
				<Pair key="title"><String>The Unfinished Swan</String></Pair>
				<Pair key="info"><String>NPJA00087 - 1440.18 Mb</String></Pair>
				<Pair key="ingame"><String>disable</String></Pair>
			</Table>
			<Table key="psnstuff_PSN_JP_item_208">
				<Pair key="icon"><String>/dev_hdd0/game/DARKSTORE/USRDIR/icons/download.png</String></Pair>
				<Pair key="title"><String>TOKYO JUNGLE PlayStation3 the Best</String></Pair>
				<Pair key="info"><String>NPJA00075 - 1787.34 Mb</String></Pair>
				<Pair key="ingame"><String>disable</String></Pair>
			</Table>
			<Table key="psnstuff_PSN_JP_item_209">
				<Pair key="icon"><String>/dev_hdd0/game/DARKSTORE/USRDIR/icons/download.png</String></Pair>
				<Pair key="title"><String>Tom Clancy's EndWar</String></Pair>
				<Pair key="info"><String>NPJB00247 - 6343.72 Mb</String></Pair>
				<Pair key="ingame"><String>disable</String></Pair>
			</Table>
			<Table key="psnstuff_PSN_JP_item_210">
				<Pair key="icon"><String>/dev_hdd0/game/DARKSTORE/USRDIR/icons/download.png</String></Pair>
				<Pair key="title"><String>Tom Clancy's Rainbow Six: Vegas</String></Pair>
				<Pair key="info"><String>NPJB00199 - 9791.37 Mb</String></Pair>
				<Pair key="ingame"><String>disable</String></Pair>
			</Table>
			<Table key="psnstuff_PSN_JP_item_211">
				<Pair key="icon"><String>/dev_hdd0/game/DARKSTORE/USRDIR/icons/download.png</String></Pair>
				<Pair key="title"><String>TOY HOME</String></Pair>
				<Pair key="info"><String>NPJA00015 - 629.45 Mb</String></Pair>
				<Pair key="ingame"><String>disable</String></Pair>
			</Table>
			<Table key="psnstuff_PSN_JP_item_212">
				<Pair key="icon"><String>/dev_hdd0/game/DARKSTORE/USRDIR/icons/download.png</String></Pair>
				<Pair key="title"><String>Toybox Turbos</String></Pair>
				<Pair key="info"><String>NPJB00655 - 232.06 Mb</String></Pair>
				<Pair key="ingame"><String>disable</String></Pair>
			</Table>
			<Table key="psnstuff_PSN_JP_item_213">
				<Pair key="icon"><String>/dev_hdd0/game/DARKSTORE/USRDIR/icons/download.png</String></Pair>
				<Pair key="title"><String>TV Show King</String></Pair>
				<Pair key="info"><String>NPJB90218 - 242.36 Mb</String></Pair>
				<Pair key="ingame"><String>disable</String></Pair>
			</Table>
		</Attributes>

		<Items>
			<Query
				class="type:x-xmb/folder-pixmap"
				key="psnstuff_PSN_JP_item_189"
				attr="psnstuff_PSN_JP_item_189"
				src="#psnstuff_PSN_JP_item_189_link"
			/>
			<Query
				class="type:x-xmb/folder-pixmap"
				key="psnstuff_PSN_JP_item_190"
				attr="psnstuff_PSN_JP_item_190"
				src="#psnstuff_PSN_JP_item_190_link"
			/>
			<Query
				class="type:x-xmb/folder-pixmap"
				key="psnstuff_PSN_JP_item_191"
				attr="psnstuff_PSN_JP_item_191"
				src="#psnstuff_PSN_JP_item_191_link"
			/>
			<Query
				class="type:x-xmb/folder-pixmap"
				key="psnstuff_PSN_JP_item_192"
				attr="psnstuff_PSN_JP_item_192"
				src="#psnstuff_PSN_JP_item_192_link"
			/>
			<Query
				class="type:x-xmb/folder-pixmap"
				key="psnstuff_PSN_JP_item_193"
				attr="psnstuff_PSN_JP_item_193"
				src="#psnstuff_PSN_JP_item_193_link"
			/>
			<Query
				class="type:x-xmb/folder-pixmap"
				key="psnstuff_PSN_JP_item_194"
				attr="psnstuff_PSN_JP_item_194"
				src="#psnstuff_PSN_JP_item_194_link"
			/>
			<Query
				class="type:x-xmb/folder-pixmap"
				key="psnstuff_PSN_JP_item_195"
				attr="psnstuff_PSN_JP_item_195"
				src="#psnstuff_PSN_JP_item_195_link"
			/>
			<Query
				class="type:x-xmb/folder-pixmap"
				key="psnstuff_PSN_JP_item_196"
				attr="psnstuff_PSN_JP_item_196"
				src="#psnstuff_PSN_JP_item_196_link"
			/>
			<Query
				class="type:x-xmb/folder-pixmap"
				key="psnstuff_PSN_JP_item_197"
				attr="psnstuff_PSN_JP_item_197"
				src="#psnstuff_PSN_JP_item_197_link"
			/>
			<Query
				class="type:x-xmb/folder-pixmap"
				key="psnstuff_PSN_JP_item_198"
				attr="psnstuff_PSN_JP_item_198"
				src="#psnstuff_PSN_JP_item_198_link"
			/>
			<Query
				class="type:x-xmb/folder-pixmap"
				key="psnstuff_PSN_JP_item_199"
				attr="psnstuff_PSN_JP_item_199"
				src="#psnstuff_PSN_JP_item_199_link"
			/>
			<Query
				class="type:x-xmb/folder-pixmap"
				key="psnstuff_PSN_JP_item_200"
				attr="psnstuff_PSN_JP_item_200"
				src="#psnstuff_PSN_JP_item_200_link"
			/>
			<Query
				class="type:x-xmb/folder-pixmap"
				key="psnstuff_PSN_JP_item_201"
				attr="psnstuff_PSN_JP_item_201"
				src="#psnstuff_PSN_JP_item_201_link"
			/>
			<Query
				class="type:x-xmb/folder-pixmap"
				key="psnstuff_PSN_JP_item_202"
				attr="psnstuff_PSN_JP_item_202"
				src="#psnstuff_PSN_JP_item_202_link"
			/>
			<Query
				class="type:x-xmb/folder-pixmap"
				key="psnstuff_PSN_JP_item_203"
				attr="psnstuff_PSN_JP_item_203"
				src="#psnstuff_PSN_JP_item_203_link"
			/>
			<Query
				class="type:x-xmb/folder-pixmap"
				key="psnstuff_PSN_JP_item_204"
				attr="psnstuff_PSN_JP_item_204"
				src="#psnstuff_PSN_JP_item_204_link"
			/>
			<Query
				class="type:x-xmb/folder-pixmap"
				key="psnstuff_PSN_JP_item_205"
				attr="psnstuff_PSN_JP_item_205"
				src="#psnstuff_PSN_JP_item_205_link"
			/>
			<Query
				class="type:x-xmb/folder-pixmap"
				key="psnstuff_PSN_JP_item_206"
				attr="psnstuff_PSN_JP_item_206"
				src="#psnstuff_PSN_JP_item_206_link"
			/>
			<Query
				class="type:x-xmb/folder-pixmap"
				key="psnstuff_PSN_JP_item_207"
				attr="psnstuff_PSN_JP_item_207"
				src="#psnstuff_PSN_JP_item_207_link"
			/>
			<Query
				class="type:x-xmb/folder-pixmap"
				key="psnstuff_PSN_JP_item_208"
				attr="psnstuff_PSN_JP_item_208"
				src="#psnstuff_PSN_JP_item_208_link"
			/>
			<Query
				class="type:x-xmb/folder-pixmap"
				key="psnstuff_PSN_JP_item_209"
				attr="psnstuff_PSN_JP_item_209"
				src="#psnstuff_PSN_JP_item_209_link"
			/>
			<Query
				class="type:x-xmb/folder-pixmap"
				key="psnstuff_PSN_JP_item_210"
				attr="psnstuff_PSN_JP_item_210"
				src="#psnstuff_PSN_JP_item_210_link"
			/>
			<Query
				class="type:x-xmb/folder-pixmap"
				key="psnstuff_PSN_JP_item_211"
				attr="psnstuff_PSN_JP_item_211"
				src="#psnstuff_PSN_JP_item_211_link"
			/>
			<Query
				class="type:x-xmb/folder-pixmap"
				key="psnstuff_PSN_JP_item_212"
				attr="psnstuff_PSN_JP_item_212"
				src="#psnstuff_PSN_JP_item_212_link"
			/>
			<Query
				class="type:x-xmb/folder-pixmap"
				key="psnstuff_PSN_JP_item_213"
				attr="psnstuff_PSN_JP_item_213"
				src="#psnstuff_PSN_JP_item_213_link"
			/>
		</Items>
	</View>

	<View id="psnstuff_PSN_JP_item_189_link">
	
        <Attributes>
            <Table key="psnstuff_PSN_JP_link_189">
                <Pair key="info"><String>net_package_install</String></Pair>
                <Pair key="pkg_src"><String>http://zeus.dl.playstation.net/cdn/JP0700/NPJB00416_00/wqLwEPeVmCAIFarHiZvlZMtSjqiRpKhHwXFDuKZHPRYcnncuoVZWExxFRrdfAyZEWCNEzfoVKdyMJECcFgFkuECTcROpvtThvGxUL.pkg</String></Pair>
                <Pair key="pkg_src_qa"><String>http://zeus.dl.playstation.net/cdn/JP0700/NPJB00416_00/wqLwEPeVmCAIFarHiZvlZMtSjqiRpKhHwXFDuKZHPRYcnncuoVZWExxFRrdfAyZEWCNEzfoVKdyMJECcFgFkuECTcROpvtThvGxUL.pkg</String></Pair>
                <Pair key="content_name"><String>tool_pkg_install_pc</String></Pair>
                <Pair key="content_id"><String>JP0700-NPJB00416_00-TOSYMPHONIAHDD01</String></Pair>
                <Pair key="prod_pict_path"><String>/dev_hdd0/game/DARKSTORE/USRDIR/icons/download.png</String></Pair>
            </Table>
        </Attributes>
		
        <Items>
            <Item class="type:x-xmb/xmlnpsignup" key="psnstuff_PSN_JP_link_189" attr="psnstuff_PSN_JP_link_189"/>
        </Items>
		
    </View>
	<View id="psnstuff_PSN_JP_item_190_link">
	
        <Attributes>
            <Table key="psnstuff_PSN_JP_link_190">
                <Pair key="info"><String>net_package_install</String></Pair>
                <Pair key="pkg_src"><String>http://zeus.dl.playstation.net/cdn/JP0700/NPJB00421_00/ZCjjYCZrvOZWsPGkpsSVheVKoitQPOdlXNnbGMJRDtFGhsBGRIoKTnxSqEvvowYtKaMZUxWfkopYhiNikpXRYeOympOiEUHVlTPMl.pkg</String></Pair>
                <Pair key="pkg_src_qa"><String>http://zeus.dl.playstation.net/cdn/JP0700/NPJB00421_00/ZCjjYCZrvOZWsPGkpsSVheVKoitQPOdlXNnbGMJRDtFGhsBGRIoKTnxSqEvvowYtKaMZUxWfkopYhiNikpXRYeOympOiEUHVlTPMl.pkg</String></Pair>
                <Pair key="content_name"><String>tool_pkg_install_pc</String></Pair>
                <Pair key="content_id"><String>JP0700-NPJB00421_00-TOSRATATOSKHDD01</String></Pair>
                <Pair key="prod_pict_path"><String>/dev_hdd0/game/DARKSTORE/USRDIR/icons/download.png</String></Pair>
            </Table>
        </Attributes>
		
        <Items>
            <Item class="type:x-xmb/xmlnpsignup" key="psnstuff_PSN_JP_link_190" attr="psnstuff_PSN_JP_link_190"/>
        </Items>
		
    </View>
	<View id="psnstuff_PSN_JP_item_191_link">
	
        <Attributes>
            <Table key="psnstuff_PSN_JP_link_191">
                <Pair key="info"><String>net_package_install</String></Pair>
                <Pair key="pkg_src"><String>http://zeus.dl.playstation.net/cdn/JP0132/NPJB90228_00/0Dosj7yj2InMIThyGn9BL6TIol0kld71lJes609BT2WfncNgdVF7eMpForp4SXTcS2Ql2rlyWyP8DJbDgEKT1lSRKdNT7rLPa9IuG.pkg</String></Pair>
                <Pair key="pkg_src_qa"><String>http://zeus.dl.playstation.net/cdn/JP0132/NPJB90228_00/0Dosj7yj2InMIThyGn9BL6TIol0kld71lJes609BT2WfncNgdVF7eMpForp4SXTcS2Ql2rlyWyP8DJbDgEKT1lSRKdNT7rLPa9IuG.pkg</String></Pair>
                <Pair key="content_name"><String>tool_pkg_install_pc</String></Pair>
                <Pair key="content_id"><String>JP0132-NPJB90228_00-TANKBATTLE00DEMO</String></Pair>
                <Pair key="prod_pict_path"><String>/dev_hdd0/game/DARKSTORE/USRDIR/icons/download.png</String></Pair>
            </Table>
        </Attributes>
		
        <Items>
            <Item class="type:x-xmb/xmlnpsignup" key="psnstuff_PSN_JP_link_191" attr="psnstuff_PSN_JP_link_191"/>
        </Items>
		
    </View>
	<View id="psnstuff_PSN_JP_item_192_link">
	
        <Attributes>
            <Table key="psnstuff_PSN_JP_link_192">
                <Pair key="info"><String>net_package_install</String></Pair>
                <Pair key="pkg_src"><String>http://zeus.dl.playstation.net/cdn/JP0700/NPJB00404_00/KOIbBQeAeDwAXgiFPakdlJFAZvtWxHAgLcCOlHHKXSLwMXJfVYRFltMBuvAwvKqvQgJdPsUBVorNsmZHUBNjtChNsGCACCMMoNDgy.pkg</String></Pair>
                <Pair key="pkg_src_qa"><String>http://zeus.dl.playstation.net/cdn/JP0700/NPJB00404_00/KOIbBQeAeDwAXgiFPakdlJFAZvtWxHAgLcCOlHHKXSLwMXJfVYRFltMBuvAwvKqvQgJdPsUBVorNsmZHUBNjtChNsGCACCMMoNDgy.pkg</String></Pair>
                <Pair key="content_name"><String>tool_pkg_install_pc</String></Pair>
                <Pair key="content_id"><String>JP0700-NPJB00404_00-TEKKENREVOLUTION</String></Pair>
                <Pair key="prod_pict_path"><String>/dev_hdd0/game/DARKSTORE/USRDIR/icons/download.png</String></Pair>
            </Table>
        </Attributes>
		
        <Items>
            <Item class="type:x-xmb/xmlnpsignup" key="psnstuff_PSN_JP_link_192" attr="psnstuff_PSN_JP_link_192"/>
        </Items>
		
    </View>
	<View id="psnstuff_PSN_JP_item_193_link">
	
        <Attributes>
            <Table key="psnstuff_PSN_JP_link_193">
                <Pair key="info"><String>net_package_install</String></Pair>
                <Pair key="pkg_src"><String>http://zeus.dl.playstation.net/cdn/JP0700/NPJB00236_00/NoaOLlRniUqJxlPZjUGtDrzBdGwnzWheWwiLaPwueyJaQuCXVQvnCOHmLjNEWagAxFYPStbGLfxstCSTvdNZkLKTkEmWLafLJGnzy.pkg</String></Pair>
                <Pair key="pkg_src_qa"><String>http://zeus.dl.playstation.net/cdn/JP0700/NPJB00236_00/NoaOLlRniUqJxlPZjUGtDrzBdGwnzWheWwiLaPwueyJaQuCXVQvnCOHmLjNEWagAxFYPStbGLfxstCSTvdNZkLKTkEmWLafLJGnzy.pkg</String></Pair>
                <Pair key="content_name"><String>tool_pkg_install_pc</String></Pair>
                <Pair key="content_id"><String>JP0700-NPJB00236_00-TEKKENTAG2DLGAME</String></Pair>
                <Pair key="prod_pict_path"><String>/dev_hdd0/game/DARKSTORE/USRDIR/icons/download.png</String></Pair>
            </Table>
        </Attributes>
		
        <Items>
            <Item class="type:x-xmb/xmlnpsignup" key="psnstuff_PSN_JP_link_193" attr="psnstuff_PSN_JP_link_193"/>
        </Items>
		
    </View>
	<View id="psnstuff_PSN_JP_item_194_link">
	
        <Attributes>
            <Table key="psnstuff_PSN_JP_link_194">
                <Pair key="info"><String>net_package_install</String></Pair>
                <Pair key="pkg_src"><String>http://ares.dl.playstation.net/cdn/JP0365/NPJB00383_00/vIkMqCXowsveoGQjfehnasGCwSeEmkznKIqIbzzmdnSfywqBgaohnfoPtxoRRNchQChdmElvduTtLYhxyXzwNIXFtmolbdyYIrKca.pkg</String></Pair>
                <Pair key="pkg_src_qa"><String>http://ares.dl.playstation.net/cdn/JP0365/NPJB00383_00/vIkMqCXowsveoGQjfehnasGCwSeEmkznKIqIbzzmdnSfywqBgaohnfoPtxoRRNchQChdmElvduTtLYhxyXzwNIXFtmolbdyYIrKca.pkg</String></Pair>
                <Pair key="content_name"><String>tool_pkg_install_pc</String></Pair>
                <Pair key="content_id"><String>JP0365-NPJB00383_00-TERRARIA00000001</String></Pair>
                <Pair key="prod_pict_path"><String>/dev_hdd0/game/DARKSTORE/USRDIR/icons/download.png</String></Pair>
            </Table>
        </Attributes>
		
        <Items>
            <Item class="type:x-xmb/xmlnpsignup" key="psnstuff_PSN_JP_link_194" attr="psnstuff_PSN_JP_link_194"/>
        </Items>
		
    </View>
	<View id="psnstuff_PSN_JP_item_195_link">
	
        <Attributes>
            <Table key="psnstuff_PSN_JP_link_195">
                <Pair key="info"><String>net_package_install</String></Pair>
                <Pair key="pkg_src"><String>http://ares.dl.playstation.net/cdn/JP0006/NPJB00136_00/lKzDJUHiqAkJEBbanyCTfDtioyjMJOsgHVsIrTAWhFQsfMBciVYAUvjchRNEdeQIXfDkEAJJRHoHHTQwCjWRiHBnFMcTRJuLFqmXD.pkg</String></Pair>
                <Pair key="pkg_src_qa"><String>http://ares.dl.playstation.net/cdn/JP0006/NPJB00136_00/lKzDJUHiqAkJEBbanyCTfDtioyjMJOsgHVsIrTAWhFQsfMBciVYAUvjchRNEdeQIXfDkEAJJRHoHHTQwCjWRiHBnFMcTRJuLFqmXD.pkg</String></Pair>
                <Pair key="content_name"><String>tool_pkg_install_pc</String></Pair>
                <Pair key="content_id"><String>JP0006-NPJB00136_00-TETRISDEMO000000</String></Pair>
                <Pair key="prod_pict_path"><String>/dev_hdd0/game/DARKSTORE/USRDIR/icons/download.png</String></Pair>
            </Table>
        </Attributes>
		
        <Items>
            <Item class="type:x-xmb/xmlnpsignup" key="psnstuff_PSN_JP_link_195" attr="psnstuff_PSN_JP_link_195"/>
        </Items>
		
    </View>
	<View id="psnstuff_PSN_JP_item_196_link">
	
        <Attributes>
            <Table key="psnstuff_PSN_JP_link_196">
                <Pair key="info"><String>net_package_install</String></Pair>
                <Pair key="pkg_src"><String>http://ares.dl.playstation.net/cdn/JP0177/NPJB00317_00/ATuIdOrTCtPcXWBbkppQYrtJoMvXkSttawfwwUcISNbXoVcfaQSSIoBviEqddfwvhbQIfWGyiSipwvqOBSsJsznSCZXvvGoNeXAXK.pkg</String></Pair>
                <Pair key="pkg_src_qa"><String>http://ares.dl.playstation.net/cdn/JP0177/NPJB00317_00/ATuIdOrTCtPcXWBbkppQYrtJoMvXkSttawfwwUcISNbXoVcfaQSSIoBviEqddfwvhbQIfWGyiSipwvqOBSsJsznSCZXvvGoNeXAXK.pkg</String></Pair>
                <Pair key="content_name"><String>tool_pkg_install_pc</String></Pair>
                <Pair key="content_id"><String>JP0177-NPJB00317_00-CAVEGAME00000000</String></Pair>
                <Pair key="prod_pict_path"><String>/dev_hdd0/game/DARKSTORE/USRDIR/icons/download.png</String></Pair>
            </Table>
        </Attributes>
		
        <Items>
            <Item class="type:x-xmb/xmlnpsignup" key="psnstuff_PSN_JP_link_196" attr="psnstuff_PSN_JP_link_196"/>
        </Items>
		
    </View>
	<View id="psnstuff_PSN_JP_item_197_link">
	
        <Attributes>
            <Table key="psnstuff_PSN_JP_link_197">
                <Pair key="info"><String>net_package_install</String></Pair>
                <Pair key="pkg_src"><String>http://zeus.dl.playstation.net/cdn/JP0230/NPJB00205_00/GKpYTAwiVtMQGrylyTyCMKssdjNCuooMDFndsegDuAUQILCXhepnexZoFfqTpHToiXdhyAhapOJItkQKQUAEpYErPZoIMQMDaKiYn.pkg</String></Pair>
                <Pair key="pkg_src_qa"><String>http://zeus.dl.playstation.net/cdn/JP0230/NPJB00205_00/GKpYTAwiVtMQGrylyTyCMKssdjNCuooMDFndsegDuAUQILCXhepnexZoFfqTpHToiXdhyAhapOJItkQKQUAEpYErPZoIMQMDaKiYn.pkg</String></Pair>
                <Pair key="content_name"><String>tool_pkg_install_pc</String></Pair>
                <Pair key="content_id"><String>JP0230-NPJB00205_00-THEDARKNESSIIPSN</String></Pair>
                <Pair key="prod_pict_path"><String>/dev_hdd0/game/DARKSTORE/USRDIR/icons/download.png</String></Pair>
            </Table>
        </Attributes>
		
        <Items>
            <Item class="type:x-xmb/xmlnpsignup" key="psnstuff_PSN_JP_link_197" attr="psnstuff_PSN_JP_link_197"/>
        </Items>
		
    </View>
	<View id="psnstuff_PSN_JP_item_198_link">
	
        <Attributes>
            <Table key="psnstuff_PSN_JP_link_198">
                <Pair key="info"><String>net_package_install</String></Pair>
                <Pair key="pkg_src"><String>http://zeus.dl.playstation.net/cdn/JP0262/NPJB00615_00/UueklAJHhOtDsnXqZDuQrJyJnsXrsDCPXFcfRUNqSABfWfbqtFKQjaVzVqaxriPDjsfrzGaeZVxTfWyKqnnNyUkAnKuuuuMnjTqeQ.pkg</String></Pair>
                <Pair key="pkg_src_qa"><String>http://zeus.dl.playstation.net/cdn/JP0262/NPJB00615_00/UueklAJHhOtDsnXqZDuQrJyJnsXrsDCPXFcfRUNqSABfWfbqtFKQjaVzVqaxriPDjsfrzGaeZVxTfWyKqnnNyUkAnKuuuuMnjTqeQ.pkg</String></Pair>
                <Pair key="content_name"><String>tool_pkg_install_pc</String></Pair>
                <Pair key="content_id"><String>JP0262-NPJB00615_00-HDDBOOTPB0000001</String></Pair>
                <Pair key="prod_pict_path"><String>/dev_hdd0/game/DARKSTORE/USRDIR/icons/download.png</String></Pair>
            </Table>
        </Attributes>
		
        <Items>
            <Item class="type:x-xmb/xmlnpsignup" key="psnstuff_PSN_JP_link_198" attr="psnstuff_PSN_JP_link_198"/>
        </Items>
		
    </View>
	<View id="psnstuff_PSN_JP_item_199_link">
	
        <Attributes>
            <Table key="psnstuff_PSN_JP_link_199">
                <Pair key="info"><String>net_package_install</String></Pair>
                <Pair key="pkg_src"><String>http://ares.dl.playstation.net/cdn/JP0006/NPJB00113_00/AKSiRtnNmYQifxLbDkRiikgByezgVnGxIvNJJKnMWjybMHiWLKPCESskxhojOjrrgElYwNTrPiqhFNPOshpHKFdVQIOJLzlTdvqAz.pkg</String></Pair>
                <Pair key="pkg_src_qa"><String>http://ares.dl.playstation.net/cdn/JP0006/NPJB00113_00/AKSiRtnNmYQifxLbDkRiikgByezgVnGxIvNJJKnMWjybMHiWLKPCESskxhojOjrrgElYwNTrPiqhFNPOshpHKFdVQIOJLzlTdvqAz.pkg</String></Pair>
                <Pair key="content_name"><String>tool_pkg_install_pc</String></Pair>
                <Pair key="content_id"><String>JP0006-NPJB00113_00-HDDFANCYPANTS070</String></Pair>
                <Pair key="prod_pict_path"><String>/dev_hdd0/game/DARKSTORE/USRDIR/icons/download.png</String></Pair>
            </Table>
        </Attributes>
		
        <Items>
            <Item class="type:x-xmb/xmlnpsignup" key="psnstuff_PSN_JP_link_199" attr="psnstuff_PSN_JP_link_199"/>
        </Items>
		
    </View>
	<View id="psnstuff_PSN_JP_item_200_link">
	
        <Attributes>
            <Table key="psnstuff_PSN_JP_link_200">
                <Pair key="info"><String>net_package_install</String></Pair>
                <Pair key="pkg_src"><String>http://zeus.dl.playstation.net/cdn/JP0404/NPJB00350_00/tgrZlIVUImcUkFFDStdKmQDVPZWHZKOxQBbsuwnrwnIvFEwQupslzTfCmCBOBKnMMzzkLtbXCpVjrqyeKtjltpqXwnandVzGsicmA.pkg</String></Pair>
                <Pair key="pkg_src_qa"><String>http://zeus.dl.playstation.net/cdn/JP0404/NPJB00350_00/tgrZlIVUImcUkFFDStdKmQDVPZWHZKOxQBbsuwnrwnIvFEwQupslzTfCmCBOBKnMMzzkLtbXCpVjrqyeKtjltpqXwnandVzGsicmA.pkg</String></Pair>
                <Pair key="content_name"><String>tool_pkg_install_pc</String></Pair>
                <Pair key="content_id"><String>JP0404-NPJB00350_00-KAMIPARA00000001</String></Pair>
                <Pair key="prod_pict_path"><String>/dev_hdd0/game/DARKSTORE/USRDIR/icons/download.png</String></Pair>
            </Table>
        </Attributes>
		
        <Items>
            <Item class="type:x-xmb/xmlnpsignup" key="psnstuff_PSN_JP_link_200" attr="psnstuff_PSN_JP_link_200"/>
        </Items>
		
    </View>
	<View id="psnstuff_PSN_JP_item_201_link">
	
        <Attributes>
            <Table key="psnstuff_PSN_JP_link_201">
                <Pair key="info"><String>net_package_install</String></Pair>
                <Pair key="pkg_src"><String>http://zeus.dl.playstation.net/cdn/JP0700/NPJB00337_00/vFSiGRCiUJeXPJiNGPvCEqreQiaMkFWcQdxGFCsDzaudFMGMRkbndabaelnoZJweUbgXcrRWJucejnjmZeJQsSaJpoodUPYQaXGfi.pkg</String></Pair>
                <Pair key="pkg_src_qa"><String>http://zeus.dl.playstation.net/cdn/JP0700/NPJB00337_00/vFSiGRCiUJeXPJiNGPvCEqreQiaMkFWcQdxGFCsDzaudFMGMRkbndabaelnoZJweUbgXcrRWJucejnjmZeJQsSaJpoodUPYQaXGfi.pkg</String></Pair>
                <Pair key="content_name"><String>tool_pkg_install_pc</String></Pair>
                <Pair key="content_id"><String>JP0700-NPJB00337_00-IMAS2HDDBOOT0000</String></Pair>
                <Pair key="prod_pict_path"><String>/dev_hdd0/game/DARKSTORE/USRDIR/icons/download.png</String></Pair>
            </Table>
        </Attributes>
		
        <Items>
            <Item class="type:x-xmb/xmlnpsignup" key="psnstuff_PSN_JP_link_201" attr="psnstuff_PSN_JP_link_201"/>
        </Items>
		
    </View>
	<View id="psnstuff_PSN_JP_item_202_link">
	
        <Attributes>
            <Table key="psnstuff_PSN_JP_link_202">
                <Pair key="info"><String>net_package_install</String></Pair>
                <Pair key="pkg_src"><String>http://zeus.dl.playstation.net/cdn/JP0700/NPJB00611_00/OATuZyoacEdtvAeAlbRMELrAxNUopGMBpXRuObOhedYIYRsTTyQKZsejsogeNaQyQISfzWWTwmtWzHJJcJJZCmDifdgbOndjNTMrT.pkg</String></Pair>
                <Pair key="pkg_src_qa"><String>http://zeus.dl.playstation.net/cdn/JP0700/NPJB00611_00/OATuZyoacEdtvAeAlbRMELrAxNUopGMBpXRuObOhedYIYRsTTyQKZsejsogeNaQyQISfzWWTwmtWzHJJcJJZCmDifdgbOndjNTMrT.pkg</String></Pair>
                <Pair key="content_name"><String>tool_pkg_install_pc</String></Pair>
                <Pair key="content_id"><String>JP0700-NPJB00611_00-0000000000000000</String></Pair>
                <Pair key="prod_pict_path"><String>/dev_hdd0/game/DARKSTORE/USRDIR/icons/download.png</String></Pair>
            </Table>
        </Attributes>
		
        <Items>
            <Item class="type:x-xmb/xmlnpsignup" key="psnstuff_PSN_JP_link_202" attr="psnstuff_PSN_JP_link_202"/>
        </Items>
		
    </View>
	<View id="psnstuff_PSN_JP_item_203_link">
	
        <Attributes>
            <Table key="psnstuff_PSN_JP_link_203">
                <Pair key="info"><String>net_package_install</String></Pair>
                <Pair key="pkg_src"><String>http://zeus.dl.playstation.net/cdn/JP0576/NPJB00229_00/ewPoKYminDyndzEVKqvErYVddTFfpAQvwyGMGatIMooTgJiJgSQQLJaDohfrhGBEUpnJwAUOziSjqhVoUfgHeIuowZNwVJfZRepNJ.pkg</String></Pair>
                <Pair key="pkg_src_qa"><String>http://zeus.dl.playstation.net/cdn/JP0576/NPJB00229_00/ewPoKYminDyndzEVKqvErYVddTFfpAQvwyGMGatIMooTgJiJgSQQLJaDohfrhGBEUpnJwAUOziSjqhVoUfgHeIuowZNwVJfZRepNJ.pkg</String></Pair>
                <Pair key="content_name"><String>tool_pkg_install_pc</String></Pair>
                <Pair key="content_id"><String>JP0576-NPJB00229_00-KOFXIII000000001</String></Pair>
                <Pair key="prod_pict_path"><String>/dev_hdd0/game/DARKSTORE/USRDIR/icons/download.png</String></Pair>
            </Table>
        </Attributes>
		
        <Items>
            <Item class="type:x-xmb/xmlnpsignup" key="psnstuff_PSN_JP_link_203" attr="psnstuff_PSN_JP_link_203"/>
        </Items>
		
    </View>
	<View id="psnstuff_PSN_JP_item_204_link">
	
        <Attributes>
            <Table key="psnstuff_PSN_JP_link_204">
                <Pair key="info"><String>net_package_install</String></Pair>
                <Pair key="pkg_src"><String>http://zeus.dl.playstation.net/cdn/JP9000/NPJA00035_00/lt9nRwv52on4tTPq1gcNkMjlyf2a8Mwb76xvGhWVterJPOKnyBaonnyxLROY1XSE4UcJcNa6Nmw61bOr37gFsSaYIwjq2pl1fvuUe.pkg</String></Pair>
                <Pair key="pkg_src_qa"><String>http://zeus.dl.playstation.net/cdn/JP9000/NPJA00035_00/lt9nRwv52on4tTPq1gcNkMjlyf2a8Mwb76xvGhWVterJPOKnyBaonnyxLROY1XSE4UcJcNa6Nmw61bOr37gFsSaYIwjq2pl1fvuUe.pkg</String></Pair>
                <Pair key="content_name"><String>tool_pkg_install_pc</String></Pair>
                <Pair key="content_id"><String>JP9000-NPJA00035_00-THELASTGUYPREM00</String></Pair>
                <Pair key="prod_pict_path"><String>/dev_hdd0/game/DARKSTORE/USRDIR/icons/download.png</String></Pair>
            </Table>
        </Attributes>
		
        <Items>
            <Item class="type:x-xmb/xmlnpsignup" key="psnstuff_PSN_JP_link_204" attr="psnstuff_PSN_JP_link_204"/>
        </Items>
		
    </View>
	<View id="psnstuff_PSN_JP_item_205_link">
	
        <Attributes>
            <Table key="psnstuff_PSN_JP_link_205">
                <Pair key="info"><String>net_package_install</String></Pair>
                <Pair key="pkg_src"><String>http://zeus.dl.playstation.net/cdn/JP0425/NPJB00409_00/abiyyPppGAjgEaFIZoFBlPhelBykKrICYPMxDJHqTwFoBNHnpgEJZyjbFuXtFiRkaJrboZtFNbjZeMgqTGGqQExdtqpTaFeSaxufe.pkg</String></Pair>
                <Pair key="pkg_src_qa"><String>http://zeus.dl.playstation.net/cdn/JP0425/NPJB00409_00/abiyyPppGAjgEaFIZoFBlPhelBykKrICYPMxDJHqTwFoBNHnpgEJZyjbFuXtFiRkaJrboZtFNbjZeMgqTGGqQExdtqpTaFeSaxufe.pkg</String></Pair>
                <Pair key="content_name"><String>tool_pkg_install_pc</String></Pair>
                <Pair key="content_id"><String>JP0425-NPJB00409_00-EDSENNOKISEKIRLS</String></Pair>
                <Pair key="prod_pict_path"><String>/dev_hdd0/game/DARKSTORE/USRDIR/icons/download.png</String></Pair>
            </Table>
        </Attributes>
		
        <Items>
            <Item class="type:x-xmb/xmlnpsignup" key="psnstuff_PSN_JP_link_205" attr="psnstuff_PSN_JP_link_205"/>
        </Items>
		
    </View>
	<View id="psnstuff_PSN_JP_item_206_link">
	
        <Attributes>
            <Table key="psnstuff_PSN_JP_link_206">
                <Pair key="info"><String>net_package_install</String></Pair>
                <Pair key="pkg_src"><String>http://zeus.dl.playstation.net/cdn/JP0425/NPJB00602_00/mxpybXfZerVGaAihSbkcJsWcCstVGyGjtvutYtVpjyUdPQuMJkFiwaUcLDqfILuxktJyvEAYgJARFtyPeexRFLOfcAFGwSUVmciVK.pkg</String></Pair>
                <Pair key="pkg_src_qa"><String>http://zeus.dl.playstation.net/cdn/JP0425/NPJB00602_00/mxpybXfZerVGaAihSbkcJsWcCstVGyGjtvutYtVpjyUdPQuMJkFiwaUcLDqfILuxktJyvEAYgJARFtyPeexRFLOfcAFGwSUVmciVK.pkg</String></Pair>
                <Pair key="content_name"><String>tool_pkg_install_pc</String></Pair>
                <Pair key="content_id"><String>JP0425-NPJB00602_00-EDSENNOKISEKI2ND</String></Pair>
                <Pair key="prod_pict_path"><String>/dev_hdd0/game/DARKSTORE/USRDIR/icons/download.png</String></Pair>
            </Table>
        </Attributes>
		
        <Items>
            <Item class="type:x-xmb/xmlnpsignup" key="psnstuff_PSN_JP_link_206" attr="psnstuff_PSN_JP_link_206"/>
        </Items>
		
    </View>
	<View id="psnstuff_PSN_JP_item_207_link">
	
        <Attributes>
            <Table key="psnstuff_PSN_JP_link_207">
                <Pair key="info"><String>net_package_install</String></Pair>
                <Pair key="pkg_src"><String>http://ares.dl.playstation.net/cdn/JP9000/NPJA00087_00/VjcLEtxmVBYxvTcjcwJlwdPTQEdkXtQioKKjBbSCkvWwvRSMJWAyNEXglnUoXEGkYjtFowlRKfnPnrMhKHOCnjsMklYVyTmaXqROr.pkg</String></Pair>
                <Pair key="pkg_src_qa"><String>http://ares.dl.playstation.net/cdn/JP9000/NPJA00087_00/VjcLEtxmVBYxvTcjcwJlwdPTQEdkXtQioKKjBbSCkvWwvRSMJWAyNEXglnUoXEGkYjtFowlRKfnPnrMhKHOCnjsMklYVyTmaXqROr.pkg</String></Pair>
                <Pair key="content_name"><String>tool_pkg_install_pc</String></Pair>
                <Pair key="content_id"><String>JP9000-NPJA00087_00-UNFINISHEDSWAN00</String></Pair>
                <Pair key="prod_pict_path"><String>/dev_hdd0/game/DARKSTORE/USRDIR/icons/download.png</String></Pair>
            </Table>
        </Attributes>
		
        <Items>
            <Item class="type:x-xmb/xmlnpsignup" key="psnstuff_PSN_JP_link_207" attr="psnstuff_PSN_JP_link_207"/>
        </Items>
		
    </View>
	<View id="psnstuff_PSN_JP_item_208_link">
	
        <Attributes>
            <Table key="psnstuff_PSN_JP_link_208">
                <Pair key="info"><String>net_package_install</String></Pair>
                <Pair key="pkg_src"><String>http://zeus.dl.playstation.net/cdn/JP9000/NPJA00075_00/ORCUzzbEYnAOVysNSEseUwZQghsajXufOZKDiOjfItoxVbcybTDJcqQVdPpBHzVNejIAaqQIAQYUtRBPjhSJTrEQCzUDpBZlpuvmk.pkg</String></Pair>
                <Pair key="pkg_src_qa"><String>http://zeus.dl.playstation.net/cdn/JP9000/NPJA00075_00/ORCUzzbEYnAOVysNSEseUwZQghsajXufOZKDiOjfItoxVbcybTDJcqQVdPpBHzVNejIAaqQIAQYUtRBPjhSJTrEQCzUDpBZlpuvmk.pkg</String></Pair>
                <Pair key="content_name"><String>tool_pkg_install_pc</String></Pair>
                <Pair key="content_id"><String>JP9000-NPJA00075_00-00000020120223BR</String></Pair>
                <Pair key="prod_pict_path"><String>/dev_hdd0/game/DARKSTORE/USRDIR/icons/download.png</String></Pair>
            </Table>
        </Attributes>
		
        <Items>
            <Item class="type:x-xmb/xmlnpsignup" key="psnstuff_PSN_JP_link_208" attr="psnstuff_PSN_JP_link_208"/>
        </Items>
		
    </View>
	<View id="psnstuff_PSN_JP_item_209_link">
	
        <Attributes>
            <Table key="psnstuff_PSN_JP_link_209">
                <Pair key="info"><String>net_package_install</String></Pair>
                <Pair key="pkg_src"><String>http://zeus.dl.playstation.net/cdn/JP0001/NPJB00247_00/LhegLDuxCPFEDMTlqPjfdraxDZzOmaFlNRKKkfhpXklAUFxtsSLwbVmRgFMhocKDvPOUTaEvjADUNYrvGwPBqNcWnnyFKchnQSAVq.pkg</String></Pair>
                <Pair key="pkg_src_qa"><String>http://zeus.dl.playstation.net/cdn/JP0001/NPJB00247_00/LhegLDuxCPFEDMTlqPjfdraxDZzOmaFlNRKKkfhpXklAUFxtsSLwbVmRgFMhocKDvPOUTaEvjADUNYrvGwPBqNcWnnyFKchnQSAVq.pkg</String></Pair>
                <Pair key="content_name"><String>tool_pkg_install_pc</String></Pair>
                <Pair key="content_id"><String>JP0001-NPJB00247_00-ENDWARPS3REMPKG1</String></Pair>
                <Pair key="prod_pict_path"><String>/dev_hdd0/game/DARKSTORE/USRDIR/icons/download.png</String></Pair>
            </Table>
        </Attributes>
		
        <Items>
            <Item class="type:x-xmb/xmlnpsignup" key="psnstuff_PSN_JP_link_209" attr="psnstuff_PSN_JP_link_209"/>
        </Items>
		
    </View>
	<View id="psnstuff_PSN_JP_item_210_link">
	
        <Attributes>
            <Table key="psnstuff_PSN_JP_link_210">
                <Pair key="info"><String>net_package_install</String></Pair>
                <Pair key="pkg_src"><String>http://zeus.dl.playstation.net/cdn/JP0001/NPJB00199_00/FpgrRaIrwMqnhAFYeHEbweLljUbwOwYnWSBJBHKRpBNitsfaLMehQyudLqzIbmmcJZVErFcnuDAERKHirvikQMVyNxjXhMZehZOVC.pkg</String></Pair>
                <Pair key="pkg_src_qa"><String>http://zeus.dl.playstation.net/cdn/JP0001/NPJB00199_00/FpgrRaIrwMqnhAFYeHEbweLljUbwOwYnWSBJBHKRpBNitsfaLMehQyudLqzIbmmcJZVErFcnuDAERKHirvikQMVyNxjXhMZehZOVC.pkg</String></Pair>
                <Pair key="content_name"><String>tool_pkg_install_pc</String></Pair>
                <Pair key="content_id"><String>JP0001-NPJB00199_00-VEGAS1BLURAYPKG1</String></Pair>
                <Pair key="prod_pict_path"><String>/dev_hdd0/game/DARKSTORE/USRDIR/icons/download.png</String></Pair>
            </Table>
        </Attributes>
		
        <Items>
            <Item class="type:x-xmb/xmlnpsignup" key="psnstuff_PSN_JP_link_210" attr="psnstuff_PSN_JP_link_210"/>
        </Items>
		
    </View>
	<View id="psnstuff_PSN_JP_item_211_link">
	
        <Attributes>
            <Table key="psnstuff_PSN_JP_link_211">
                <Pair key="info"><String>net_package_install</String></Pair>
                <Pair key="pkg_src"><String>http://zeus.dl.playstation.net/cdn/JP9000/NPJA00015_00/FHGFWI196GRO8Gw3AFtsODFPeqiGMo3db07bBTKv5l1pFXUne4XtU4InypjPCVu4i8hdYuO8mAuhMxBT8u5E6aisbS99OWAs085vy.pkg</String></Pair>
                <Pair key="pkg_src_qa"><String>http://zeus.dl.playstation.net/cdn/JP9000/NPJA00015_00/FHGFWI196GRO8Gw3AFtsODFPeqiGMo3db07bBTKv5l1pFXUne4XtU4InypjPCVu4i8hdYuO8mAuhMxBT8u5E6aisbS99OWAs085vy.pkg</String></Pair>
                <Pair key="content_name"><String>tool_pkg_install_pc</String></Pair>
                <Pair key="content_id"><String>JP9000-NPJA00015_00-TOYHOME000100001</String></Pair>
                <Pair key="prod_pict_path"><String>/dev_hdd0/game/DARKSTORE/USRDIR/icons/download.png</String></Pair>
            </Table>
        </Attributes>
		
        <Items>
            <Item class="type:x-xmb/xmlnpsignup" key="psnstuff_PSN_JP_link_211" attr="psnstuff_PSN_JP_link_211"/>
        </Items>
		
    </View>
	<View id="psnstuff_PSN_JP_item_212_link">
	
        <Attributes>
            <Table key="psnstuff_PSN_JP_link_212">
                <Pair key="info"><String>net_package_install</String></Pair>
                <Pair key="pkg_src"><String>http://ares.dl.playstation.net/cdn/JP0151/NPJB00655_00/HenEVuAyhGDulSpGmRMwuMJDNWcPGsnDvoVFQUlZaZZCuyBxfcXEYpPckRMYZSDmqRePHMlbEqOTlRTmdyUNQYxJCtCClnjKeXFaC.pkg</String></Pair>
                <Pair key="pkg_src_qa"><String>http://ares.dl.playstation.net/cdn/JP0151/NPJB00655_00/HenEVuAyhGDulSpGmRMwuMJDNWcPGsnDvoVFQUlZaZZCuyBxfcXEYpPckRMYZSDmqRePHMlbEqOTlRTmdyUNQYxJCtCClnjKeXFaC.pkg</String></Pair>
                <Pair key="content_name"><String>tool_pkg_install_pc</String></Pair>
                <Pair key="content_id"><String>JP0151-NPJB00655_00-TBT000000000CERO</String></Pair>
                <Pair key="prod_pict_path"><String>/dev_hdd0/game/DARKSTORE/USRDIR/icons/download.png</String></Pair>
            </Table>
        </Attributes>
		
        <Items>
            <Item class="type:x-xmb/xmlnpsignup" key="psnstuff_PSN_JP_link_212" attr="psnstuff_PSN_JP_link_212"/>
        </Items>
		
    </View>
	<View id="psnstuff_PSN_JP_item_213_link">
	
        <Attributes>
            <Table key="psnstuff_PSN_JP_link_213">
                <Pair key="info"><String>net_package_install</String></Pair>
                <Pair key="pkg_src"><String>http://zeus.dl.playstation.net/cdn/JP0132/NPJB90218_00/NSpQEXjn6XdoMRWgVBYDpwxRPBKx4oyePYh775PoNDT8HehYTkng0wlqw8rXYsi4jLeBIrWse0Y0pmvGWVXILwhcuQBpjQ0bANK2U.pkg</String></Pair>
                <Pair key="pkg_src_qa"><String>http://zeus.dl.playstation.net/cdn/JP0132/NPJB90218_00/NSpQEXjn6XdoMRWgVBYDpwxRPBKx4oyePYh775PoNDT8HehYTkng0wlqw8rXYsi4jLeBIrWse0Y0pmvGWVXILwhcuQBpjQ0bANK2U.pkg</String></Pair>
                <Pair key="content_name"><String>tool_pkg_install_pc</String></Pair>
                <Pair key="content_id"><String>JP0132-NPJB90218_00-TVSKPSNDEMO75547</String></Pair>
                <Pair key="prod_pict_path"><String>/dev_hdd0/game/DARKSTORE/USRDIR/icons/download.png</String></Pair>
            </Table>
        </Attributes>
		
        <Items>
            <Item class="type:x-xmb/xmlnpsignup" key="psnstuff_PSN_JP_link_213" attr="psnstuff_PSN_JP_link_213"/>
        </Items>
		
    </View>

</XMBML>